[{"C":"Group 0","W":0,"Z":1204994000},{"C":"Group 2","W":0,"Z":1204994000},{"C":"Group 1","W":1,"Z":39322000},{"C":"Group 1","W":1,"Z":12691000},{"C":"Group 1","W":1,"Z":0},{"C":"Group 1","W":1,"Z":15296000},{"C":"Group 1","W":1,"Z":28037000},{"C":"Group 1","W":1,"Z":17820000},{"C":"Group 1","W":1,"Z":68415000},{"C":"Group 1","W":1,"Z":7328000},{"C":"Group 1","W":1,"Z":8762000},{"C":"Group 1","W":1,"Z":2248000},{"C":"Group 1","W":1,"Z":9279000},{"C":"Group 1","W":1,"Z":3555000},{"C":"Group 1","W":1,"Z":7580000},{"C":"Group 1","W":1,"Z":19220000},{"C":"Group 1","W":1,"Z":12449000},{"C":"Group 1","W":1,"Z":1913000},{"C":"Group 1","W":1,"Z":0},{"C":"Group 2","W":1,"Z":254525000},{"C":"Group 3","W":0,"Z":1459519000}]