[{"C":"Group 0","W":3.96,"Z":7.5},{"C":"Group 0","W":4.41,"Z":8.3},{"C":"Group 0","W":4.14,"Z":5.0},{"C":"Group 0","W":4.11,"Z":5.3},{"C":"Group 0","W":4.45,"Z":6.8},{"C":"Group 0","W":4.1,"Z":4.4},{"C":"Group 0","W":4.31,"Z":5.3},{"C":"Group 0","W":4.42,"Z":5.7},{"C":"Group 0","W":4.3,"Z":8.9},{"C":"Group 0","W":4.51,"Z":4.4},{"C":"Group 0","W":4.71,"Z":5.3},{"C":"Group 0","W":4.62,"Z":7.3},{"C":"Group 0","W":4.35,"Z":7.8},{"C":"Group 4","W":4.26,"Z":6.2},{"C":"Group 4","W":4.63,"Z":6.0},{"C":"Group 4","W":4.36,"Z":5.8},{"C":"Group 4","W":3.91,"Z":7.3},{"C":"Group 4","W":4.51,"Z":8.3},{"C":"Group 4","W":4.37,"Z":8.1},{"C":"Group 4","W":4.9,"Z":6.9},{"C":"Group 4","W":4.46,"Z":5.7},{"C":"Group 4","W":3.95,"Z":3.3},{"C":"Group 4","W":4.46,"Z":9.5},{"C":"Group 4","W":5.02,"Z":6.4},{"C":"Group 4","W":4.26,"Z":5.8},{"C":"Group 4","W":4.46,"Z":5.6},{"C":"Group 4","W":4.16,"Z":5.8},{"C":"Group 4","W":4.49,"Z":7.6},{"C":"Group 4","W":4.21,"Z":7.5},{"C":"Group 4","W":4.57,"Z":6.6},{"C":"Group 4","W":4.87,"Z":6.4},{"C":"Group 4","W":4.44,"Z":10.1},{"C":"Group 4","W":4.45,"Z":6.6},{"C":"Group 4","W":4.41,"Z":5.9},{"C":"Group 4","W":4.87,"Z":7.3},{"C":"Group 3","W":4.56,"Z":13.3},{"C":"Group 3","W":4.15,"Z":6.0},{"C":"Group 3","W":4.16,"Z":7.6},{"C":"Group 3","W":4.32,"Z":6.4},{"C":"Group 3","W":4.06,"Z":5.8},{"C":"Group 3","W":4.12,"Z":6.1},{"C":"Group 3","W":4.17,"Z":5.0},{"C":"Group 3","W":3.8,"Z":6.6},{"C":"Group 3","W":3.96,"Z":5.5},{"C":"Group 3","W":4.44,"Z":9.7},{"C":"Group 3","W":4.27,"Z":10.6},{"C":"Group 3","W":3.9,"Z":6.3},{"C":"Group 3","W":4.02,"Z":9.1},{"C":"Group 3","W":4.39,"Z":9.6},{"C":"Group 3","W":4.52,"Z":5.1},{"C":"Group 3","W":4.25,"Z":10.7},{"C":"Group 3","W":4.46,"Z":10.9},{"C":"Group 3","W":4.4,"Z":9.3},{"C":"Group 3","W":4.83,"Z":8.4},{"C":"Group 3","W":4.23,"Z":6.9},{"C":"Group 3","W":4.24,"Z":8.4},{"C":"Group 3","W":3.95,"Z":6.6},{"C":"Group 3","W":4.03,"Z":8.5},{"C":"Group 5","W":4.36,"Z":5.5},{"C":"Group 5","W":4.07,"Z":5.9},{"C":"Group 5","W":4.17,"Z":4.9},{"C":"Group 5","W":4.23,"Z":8.1},{"C":"Group 5","W":4.46,"Z":8.3},{"C":"Group 5","W":4.38,"Z":5.8},{"C":"Group 5","W":4.31,"Z":5.3},{"C":"Group 5","W":4.51,"Z":5.1},{"C":"Group 5","W":4.13,"Z":7.0},{"C":"Group 1","W":4.48,"Z":9.5},{"C":"Group 6","W":5.31,"Z":9.5},{"C":"Group 1","W":4.58,"Z":5.8},{"C":"Group 1","W":4.81,"Z":6.8},{"C":"Group 1","W":4.51,"Z":9.0},{"C":"Group 1","W":4.77,"Z":7.1},{"C":"Group 1","W":5.33,"Z":9.3},{"C":"Group 1","W":4.75,"Z":7.5},{"C":"Group 6","W":4.11,"Z":7.3},{"C":"Group 7","W":4.76,"Z":7.6},{"C":"Group 6","W":4.27,"Z":6.9},{"C":"Group 6","W":4.44,"Z":6.1},{"C":"Group 6","W":4.2,"Z":6.5},{"C":"Group 6","W":4.71,"Z":6.9},{"C":"Group 6","W":4.09,"Z":6.4},{"C":"Group 6","W":4.24,"Z":6.6},{"C":"Group 6","W":3.9,"Z":6.0},{"C":"Group 7","W":4.82,"Z":7.6},{"C":"Group 6","W":4.32,"Z":6.8},{"C":"Group 6","W":4.77,"Z":7.2},{"C":"Group 7","W":5.16,"Z":8.2},{"C":"Group 7","W":4.97,"Z":7.8},{"C":"Group 8","W":4.0,"Z":4.2},{"C":"Group 8","W":4.4,"Z":4.0},{"C":"Group 8","W":4.38,"Z":7.9},{"C":"Group 8","W":4.08,"Z":6.6},{"C":"Group 8","W":4.98,"Z":6.4},{"C":"Group 8","W":5.16,"Z":7.2},{"C":"Group 8","W":4.66,"Z":6.4},{"C":"Group 2","W":4.19,"Z":9.0},{"C":"Group 2","W":4.53,"Z":5.0},{"C":"Group 2","W":4.09,"Z":4.9},{"C":"Group 2","W":4.42,"Z":6.4},{"C":"Group 5","W":5.13,"Z":7.1},{"C":"Group 5","W":4.83,"Z":7.6},{"C":"Group 5","W":5.09,"Z":4.7},{"C":"Group 5","W":5.17,"Z":4.1},{"C":"Group 5","W":5.11,"Z":6.7},{"C":"Group 5","W":5.03,"Z":7.1},{"C":"Group 5","W":5.32,"Z":6.0},{"C":"Group 5","W":4.75,"Z":8.6},{"C":"Group 5","W":5.34,"Z":6.6},{"C":"Group 5","W":4.87,"Z":4.8},{"C":"Group 5","W":5.33,"Z":5.2},{"C":"Group 5","W":4.81,"Z":6.2},{"C":"Group 5","W":4.32,"Z":4.3},{"C":"Group 4","W":4.87,"Z":8.2},{"C":"Group 4","W":5.04,"Z":7.1},{"C":"Group 4","W":4.4,"Z":5.3},{"C":"Group 4","W":4.95,"Z":5.9},{"C":"Group 4","W":4.78,"Z":9.3},{"C":"Group 4","W":5.21,"Z":6.8},{"C":"Group 4","W":5.22,"Z":8.4},{"C":"Group 4","W":5.18,"Z":6.5},{"C":"Group 4","W":5.4,"Z":6.8},{"C":"Group 4","W":4.92,"Z":5.4},{"C":"Group 4","W":5.24,"Z":7.5},{"C":"Group 4","W":5.09,"Z":10.1},{"C":"Group 4","W":4.83,"Z":5.0},{"C":"Group 4","W":5.22,"Z":6.0},{"C":"Group 4","W":4.71,"Z":8.0},{"C":"Group 0","W":5.24,"Z":7.2},{"C":"Group 0","W":4.54,"Z":5.9},{"C":"Group 0","W":5.13,"Z":5.8},{"C":"Group 0","W":5.0,"Z":6.7},{"C":"Group 0","W":5.17,"Z":8.0},{"C":"Group 0","W":4.89,"Z":7.5},{"C":"Group 0","W":4.5,"Z":9.2},{"C":"Group 0","W":4.84,"Z":8.3},{"C":"Group 0","W":4.13,"Z":8.9},{"C":"Group 0","W":4.87,"Z":7.4},{"C":"Group 0","W":4.82,"Z":6.4},{"C":"Group 0","W":4.73,"Z":6.7},{"C":"Group 6","W":4.55,"Z":5.6},{"C":"Group 6","W":4.71,"Z":7.2},{"C":"Group 6","W":4.93,"Z":7.3},{"C":"Group 6","W":5.21,"Z":7.5},{"C":"Group 1","W":5.09,"Z":8.9},{"C":"Group 1","W":5.11,"Z":9.6},{"C":"Group 1","W":4.94,"Z":6.3},{"C":"Group 6","W":4.87,"Z":6.3},{"C":"Group 6","W":4.41,"Z":4.5},{"C":"Group 6","W":4.86,"Z":3.9},{"C":"Group 6","W":4.91,"Z":9.0},{"C":"Group 6","W":4.93,"Z":7.3},{"C":"Group 6","W":4.2,"Z":4.5},{"C":"Group 6","W":5.1,"Z":6.1},{"C":"Group 6","W":4.5,"Z":6.1},{"C":"Group 7","W":4.89,"Z":5.8},{"C":"Group 7","W":5.13,"Z":4.0},{"C":"Group 7","W":4.88,"Z":4.3},{"C":"Group 1","W":5.0,"Z":8.2},{"C":"Group 1","W":5.48,"Z":4.6},{"C":"Group 1","W":5.93,"Z":6.4},{"C":"Group 1","W":5.01,"Z":8.9},{"C":"Group 1","W":5.48,"Z":6.2},{"C":"Group 7","W":5.16,"Z":8.4},{"C":"Group 7","W":4.64,"Z":9.0},{"C":"Group 7","W":6.72,"Z":7.1},{"C":"Group 6","W":4.83,"Z":6.6},{"C":"Group 6","W":5.34,"Z":7.6},{"C":"Group 6","W":5.13,"Z":4.6},{"C":"Group 6","W":4.68,"Z":4.8},{"C":"Group 7","W":5.0,"Z":5.2},{"C":"Group 7","W":4.99,"Z":7.2},{"C":"Group 6","W":5.49,"Z":5.9},{"C":"Group 7","W":5.59,"Z":7.9},{"C":"Group 6","W":5.03,"Z":6.6},{"C":"Group 7","W":5.5,"Z":6.4},{"C":"Group 1","W":5.11,"Z":9.3},{"C":"Group 1","W":4.96,"Z":8.3},{"C":"Group 1","W":5.01,"Z":8.9},{"C":"Group 1","W":5.11,"Z":8.7},{"C":"Group 7","W":5.69,"Z":10.8},{"C":"Group 9","W":4.63,"Z":9.1},{"C":"Group 9","W":4.91,"Z":10.2},{"C":"Group 9","W":4.95,"Z":7.5},{"C":"Group 9","W":5.34,"Z":10.0},{"C":"Group 9","W":5.16,"Z":12.9},{"C":"Group 9","W":5.29,"Z":12.7},{"C":"Group 9","W":5.02,"Z":6.1},{"C":"Group 9","W":5.01,"Z":9.8},{"C":"Group 9","W":5.03,"Z":7.5},{"C":"Group 9","W":5.25,"Z":7.4},{"C":"Group 9","W":5.08,"Z":8.5},{"C":"Group 9","W":5.04,"Z":6.0},{"C":"Group 9","W":4.63,"Z":14.3},{"C":"Group 9","W":5.11,"Z":7.0},{"C":"Group 9","W":5.34,"Z":6.2},{"C":"Group 9","W":4.86,"Z":8.9},{"C":"Group 9","W":4.9,"Z":7.6},{"C":"Group 8","W":5.66,"Z":8.3},{"C":"Group 8","W":5.03,"Z":6.4},{"C":"Group 8","W":4.97,"Z":8.8},{"C":"Group 8","W":5.38,"Z":6.3}]