[{"C":"Group 0","W":213,"Z":145},{"C":"Group 1","W":32,"Z":30},{"C":"Group 2","W":3,"Z":5},{"C":"Group 3","W":739,"Z":571},{"C":"Group 4","W":1265,"Z":956},{"C":"Group 5","W":619,"Z":466},{"C":"Group 6","W":8507,"Z":7017},{"C":"Group 7","W":778,"Z":564},{"C":"Group 8","W":452,"Z":500},{"C":"Group 9","W":127,"Z":166},{"C":"Group 10","W":343,"Z":299},{"C":"Group 11","W":366,"Z":359},{"C":"Group 12","W":263,"Z":224},{"C":"Group 13","W":1154,"Z":1066},{"C":"Group 14","W":86,"Z":90},{"C":"Group 15","W":594,"Z":522},{"C":"Group 16","W":991,"Z":629},{"C":"Group 17","W":11007,"Z":8777},{"C":"Group 18","W":694,"Z":647},{"C":"Group 0","W":308,"Z":208},{"C":"Group 1","W":437,"Z":359},{"C":"Group 2","W":52,"Z":43},{"C":"Group 3","W":3934,"Z":2940},{"C":"Group 4","W":8177,"Z":5999},{"C":"Group 5","W":1890,"Z":1681},{"C":"Group 6","W":10739,"Z":10328},{"C":"Group 7","W":3846,"Z":2838},{"C":"Group 8","W":906,"Z":740},{"C":"Group 9","W":543,"Z":596},{"C":"Group 10","W":649,"Z":593},{"C":"Group 11","W":1074,"Z":857},{"C":"Group 12","W":316,"Z":293},{"C":"Group 13","W":4613,"Z":4089},{"C":"Group 14","W":348,"Z":330},{"C":"Group 15","W":1202,"Z":1230},{"C":"Group 16","W":687,"Z":553},{"C":"Group 17","W":8359,"Z":8153},{"C":"Group 18","W":1298,"Z":1303},{"C":"Group 0","W":318,"Z":269},{"C":"Group 1","W":831,"Z":814},{"C":"Group 2","W":80,"Z":112},{"C":"Group 3","W":5357,"Z":4542},{"C":"Group 4","W":12236,"Z":10064},{"C":"Group 5","W":2746,"Z":2508},{"C":"Group 6","W":8559,"Z":8985},{"C":"Group 7","W":3809,"Z":3277},{"C":"Group 8","W":1275,"Z":1221},{"C":"Group 9","W":1018,"Z":1239},{"C":"Group 10","W":771,"Z":730},{"C":"Group 11","W":1754,"Z":1512},{"C":"Group 12","W":371,"Z":336},{"C":"Group 13","W":4328,"Z":4712},{"C":"Group 14","W":331,"Z":328},{"C":"Group 15","W":1615,"Z":1740},{"C":"Group 16","W":651,"Z":599},{"C":"Group 17","W":6761,"Z":7131},{"C":"Group 18","W":1490,"Z":1544},{"C":"Group 0","W":1092,"Z":937},{"C":"Group 1","W":3943,"Z":3995},{"C":"Group 2","W":732,"Z":705},{"C":"Group 3","W":19568,"Z":17398},{"C":"Group 4","W":57360,"Z":48444},{"C":"Group 5","W":12442,"Z":12149},{"C":"Group 6","W":22382,"Z":21684},{"C":"Group 7","W":14591,"Z":12794},{"C":"Group 8","W":4499,"Z":4202},{"C":"Group 9","W":5109,"Z":5639},{"C":"Group 10","W":2337,"Z":2279},{"C":"Group 11","W":7965,"Z":7462},{"C":"Group 12","W":1649,"Z":1578},{"C":"Group 13","W":12082,"Z":12620},{"C":"Group 14","W":1060,"Z":1083},{"C":"Group 15","W":7527,"Z":7611},{"C":"Group 16","W":1789,"Z":1586},{"C":"Group 17","W":13014,"Z":13572},{"C":"Group 18","W":5201,"Z":5246},{"C":"Group 0","W":1372,"Z":1284},{"C":"Group 1","W":5712,"Z":5210},{"C":"Group 2","W":2067,"Z":1661},{"C":"Group 3","W":22076,"Z":19448},{"C":"Group 4","W":62210,"Z":54900},{"C":"Group 5","W":15334,"Z":14795},{"C":"Group 6","W":21462,"Z":20432},{"C":"Group 7","W":17585,"Z":16427},{"C":"Group 8","W":3971,"Z":3526},{"C":"Group 9","W":4842,"Z":5225},{"C":"Group 10","W":2468,"Z":2380},{"C":"Group 11","W":7089,"Z":6842},{"C":"Group 12","W":2100,"Z":1995},{"C":"Group 13","W":11012,"Z":10866},{"C":"Group 14","W":1139,"Z":1131},{"C":"Group 15","W":8598,"Z":8442},{"C":"Group 16","W":1812,"Z":1559},{"C":"Group 17","W":8811,"Z":8435},{"C":"Group 18","W":5937,"Z":5922},{"C":"Group 0","W":1008,"Z":1018},{"C":"Group 1","W":5397,"Z":5681},{"C":"Group 2","W":2137,"Z":2004},{"C":"Group 3","W":14368,"Z":14240},{"C":"Group 4","W":50848,"Z":47413},{"C":"Group 5","W":11958,"Z":12535},{"C":"Group 6","W":15777,"Z":16137},{"C":"Group 7","W":12378,"Z":12206},{"C":"Group 8","W":3917,"Z":3374},{"C":"Group 9","W":4181,"Z":4358},{"C":"Group 10","W":1749,"Z":1912},{"C":"Group 11","W":6240,"Z":6058},{"C":"Group 12","W":1819,"Z":1815},{"C":"Group 13","W":7528,"Z":7946},{"C":"Group 14","W":1261,"Z":1321},{"C":"Group 15","W":7019,"Z":7412},{"C":"Group 16","W":1468,"Z":1392},{"C":"Group 17","W":4348,"Z":4468},{"C":"Group 18","W":4438,"Z":5017},{"C":"Group 0","W":501,"Z":537},{"C":"Group 1","W":1490,"Z":1725},{"C":"Group 2","W":581,"Z":597},{"C":"Group 3","W":5508,"Z":5612},{"C":"Group 4","W":20768,"Z":20941},{"C":"Group 5","W":4884,"Z":5718},{"C":"Group 6","W":7905,"Z":8597},{"C":"Group 7","W":4844,"Z":5256},{"C":"Group 8","W":1204,"Z":1307},{"C":"Group 9","W":1792,"Z":2365},{"C":"Group 10","W":1036,"Z":1175},{"C":"Group 11","W":2546,"Z":2962},{"C":"Group 12","W":634,"Z":703},{"C":"Group 13","W":3446,"Z":3855},{"C":"Group 14","W":667,"Z":850},{"C":"Group 15","W":2989,"Z":3534},{"C":"Group 16","W":836,"Z":854},{"C":"Group 17","W":1613,"Z":1601},{"C":"Group 18","W":2087,"Z":2519},{"C":"Group 0","W":249,"Z":270},{"C":"Group 1","W":127,"Z":148},{"C":"Group 2","W":29,"Z":44},{"C":"Group 3","W":1207,"Z":1144},{"C":"Group 4","W":2303,"Z":2307},{"C":"Group 5","W":1228,"Z":1431},{"C":"Group 6","W":4143,"Z":4176},{"C":"Group 7","W":1022,"Z":1197},{"C":"Group 8","W":248,"Z":256},{"C":"Group 9","W":513,"Z":619},{"C":"Group 10","W":652,"Z":661},{"C":"Group 11","W":666,"Z":724},{"C":"Group 12","W":162,"Z":181},{"C":"Group 13","W":1827,"Z":1737},{"C":"Group 14","W":221,"Z":262},{"C":"Group 15","W":971,"Z":1064},{"C":"Group 16","W":555,"Z":526},{"C":"Group 17","W":877,"Z":795},{"C":"Group 18","W":1004,"Z":1074},{"C":"Group 0","W":117,"Z":77},{"C":"Group 1","W":11,"Z":3},{"C":"Group 2","W":10,"Z":7},{"C":"Group 3","W":200,"Z":148},{"C":"Group 4","W":684,"Z":537},{"C":"Group 5","W":315,"Z":263},{"C":"Group 6","W":9045,"Z":8045},{"C":"Group 7","W":660,"Z":403},{"C":"Group 8","W":493,"Z":479},{"C":"Group 9","W":430,"Z":397},{"C":"Group 10","W":375,"Z":312},{"C":"Group 11","W":649,"Z":661},{"C":"Group 12","W":231,"Z":216},{"C":"Group 13","W":836,"Z":682},{"C":"Group 14","W":187,"Z":275},{"C":"Group 15","W":2433,"Z":2017},{"C":"Group 16","W":870,"Z":531},{"C":"Group 17","W":12771,"Z":10996},{"C":"Group 18","W":859,"Z":719},{"C":"Group 0","W":140,"Z":85},{"C":"Group 1","W":24,"Z":16},{"C":"Group 2","W":18,"Z":11},{"C":"Group 3","W":413,"Z":294},{"C":"Group 4","W":3332,"Z":2087},{"C":"Group 5","W":877,"Z":697},{"C":"Group 6","W":12953,"Z":13274},{"C":"Group 7","W":2076,"Z":1375},{"C":"Group 8","W":1186,"Z":862},{"C":"Group 9","W":2359,"Z":2167},{"C":"Group 10","W":681,"Z":688},{"C":"Group 11","W":1502,"Z":1327},{"C":"Group 12","W":410,"Z":356},{"C":"Group 13","W":3203,"Z":2511},{"C":"Group 14","W":697,"Z":660},{"C":"Group 15","W":7142,"Z":7360},{"C":"Group 16","W":644,"Z":535},{"C":"Group 17","W":10856,"Z":10781},{"C":"Group 18","W":1311,"Z":1214},{"C":"Group 0","W":183,"Z":127},{"C":"Group 1","W":36,"Z":27},{"C":"Group 2","W":32,"Z":26},{"C":"Group 3","W":532,"Z":439},{"C":"Group 4","W":4999,"Z":3678},{"C":"Group 5","W":1234,"Z":1197},{"C":"Group 6","W":9502,"Z":9903},{"C":"Group 7","W":1705,"Z":1463},{"C":"Group 8","W":1691,"Z":1407},{"C":"Group 9","W":3430,"Z":3701},{"C":"Group 10","W":633,"Z":672},{"C":"Group 11","W":2223,"Z":2126},{"C":"Group 12","W":547,"Z":463},{"C":"Group 13","W":3462,"Z":3122},{"C":"Group 14","W":514,"Z":511},{"C":"Group 15","W":9790,"Z":10604},{"C":"Group 16","W":565,"Z":530},{"C":"Group 17","W":7935,"Z":8588},{"C":"Group 18","W":1293,"Z":1425},{"C":"Group 0","W":474,"Z":405},{"C":"Group 1","W":183,"Z":180},{"C":"Group 2","W":237,"Z":177},{"C":"Group 3","W":2166,"Z":1852},{"C":"Group 4","W":23127,"Z":18142},{"C":"Group 5","W":5650,"Z":5391},{"C":"Group 6","W":22563,"Z":21258},{"C":"Group 7","W":6289,"Z":5291},{"C":"Group 8","W":5081,"Z":4262},{"C":"Group 9","W":11375,"Z":11762},{"C":"Group 10","W":1910,"Z":1959},{"C":"Group 11","W":8064,"Z":7900},{"C":"Group 12","W":1940,"Z":1776},{"C":"Group 13","W":9266,"Z":8696},{"C":"Group 14","W":1559,"Z":1625},{"C":"Group 15","W":37391,"Z":39681},{"C":"Group 16","W":1375,"Z":1323},{"C":"Group 17","W":16035,"Z":15479},{"C":"Group 18","W":4522,"Z":4582},{"C":"Group 0","W":615,"Z":469},{"C":"Group 1","W":322,"Z":291},{"C":"Group 2","W":510,"Z":429},{"C":"Group 3","W":3004,"Z":2492},{"C":"Group 4","W":30732,"Z":25109},{"C":"Group 5","W":6684,"Z":6606},{"C":"Group 6","W":25970,"Z":23632},{"C":"Group 7","W":6785,"Z":6067},{"C":"Group 8","W":4803,"Z":3788},{"C":"Group 9","W":12085,"Z":12478},{"C":"Group 10","W":2092,"Z":2032},{"C":"Group 11","W":8290,"Z":7987},{"C":"Group 12","W":2313,"Z":2165},{"C":"Group 13","W":8994,"Z":8276},{"C":"Group 14","W":1788,"Z":1835},{"C":"Group 15","W":40862,"Z":41008},{"C":"Group 16","W":1488,"Z":1403},{"C":"Group 17","W":14614,"Z":13330},{"C":"Group 18","W":4965,"Z":5139},{"C":"Group 0","W":474,"Z":440},{"C":"Group 1","W":252,"Z":273},{"C":"Group 2","W":492,"Z":523},{"C":"Group 3","W":2204,"Z":2141},{"C":"Group 4","W":24653,"Z":21904},{"C":"Group 5","W":5072,"Z":5369},{"C":"Group 6","W":21548,"Z":21212},{"C":"Group 7","W":3921,"Z":4078},{"C":"Group 8","W":3885,"Z":3347},{"C":"Group 9","W":9357,"Z":10192},{"C":"Group 10","W":1851,"Z":1897},{"C":"Group 11","W":6241,"Z":6617},{"C":"Group 12","W":1772,"Z":1784},{"C":"Group 13","W":6283,"Z":6137},{"C":"Group 14","W":1979,"Z":2004},{"C":"Group 15","W":32824,"Z":35981},{"C":"Group 16","W":1144,"Z":1104},{"C":"Group 17","W":8294,"Z":8201},{"C":"Group 18","W":4384,"Z":4752},{"C":"Group 0","W":221,"Z":238},{"C":"Group 1","W":88,"Z":97},{"C":"Group 2","W":167,"Z":185},{"C":"Group 3","W":957,"Z":1054},{"C":"Group 4","W":9858,"Z":9349},{"C":"Group 5","W":1878,"Z":2263},{"C":"Group 6","W":11448,"Z":12129},{"C":"Group 7","W":1192,"Z":1435},{"C":"Group 8","W":1144,"Z":1165},{"C":"Group 9","W":3446,"Z":4611},{"C":"Group 10","W":843,"Z":1091},{"C":"Group 11","W":2194,"Z":2687},{"C":"Group 12","W":631,"Z":760},{"C":"Group 13","W":2395,"Z":2561},{"C":"Group 14","W":790,"Z":1034},{"C":"Group 15","W":12744,"Z":15271},{"C":"Group 16","W":598,"Z":584},{"C":"Group 17","W":3854,"Z":3669},{"C":"Group 18","W":2473,"Z":2689},{"C":"Group 0","W":112,"Z":121},{"C":"Group 1","W":23,"Z":30},{"C":"Group 2","W":17,"Z":22},{"C":"Group 3","W":386,"Z":368},{"C":"Group 4","W":1362,"Z":1280},{"C":"Group 5","W":465,"Z":511},{"C":"Group 6","W":4518,"Z":4734},{"C":"Group 7","W":229,"Z":224},{"C":"Group 8","W":194,"Z":222},{"C":"Group 9","W":614,"Z":726},{"C":"Group 10","W":341,"Z":405},{"C":"Group 11","W":652,"Z":644},{"C":"Group 12","W":139,"Z":158},{"C":"Group 13","W":916,"Z":855},{"C":"Group 14","W":195,"Z":212},{"C":"Group 15","W":3057,"Z":3470},{"C":"Group 16","W":293,"Z":288},{"C":"Group 17","W":1631,"Z":1588},{"C":"Group 18","W":1126,"Z":1205}]