[{"C":"Group 0","W":264,"Z":177},{"C":"Group 1","W":24,"Z":14},{"C":"Group 2","W":10,"Z":13},{"C":"Group 3","W":2711,"Z":1887},{"C":"Group 4","W":2973,"Z":1937},{"C":"Group 5","W":1050,"Z":927},{"C":"Group 6","W":14104,"Z":11200},{"C":"Group 7","W":595,"Z":625},{"C":"Group 8","W":979,"Z":821},{"C":"Group 9","W":176,"Z":165},{"C":"Group 10","W":698,"Z":598},{"C":"Group 11","W":732,"Z":638},{"C":"Group 12","W":603,"Z":392},{"C":"Group 13","W":2937,"Z":2761},{"C":"Group 14","W":341,"Z":341},{"C":"Group 15","W":704,"Z":798},{"C":"Group 16","W":2373,"Z":2189},{"C":"Group 17","W":16437,"Z":15816},{"C":"Group 18","W":1703,"Z":1509},{"C":"Group 0","W":328,"Z":349},{"C":"Group 1","W":116,"Z":77},{"C":"Group 2","W":52,"Z":49},{"C":"Group 3","W":6561,"Z":5065},{"C":"Group 4","W":13602,"Z":9516},{"C":"Group 5","W":2807,"Z":2619},{"C":"Group 6","W":15330,"Z":15695},{"C":"Group 7","W":3478,"Z":3955},{"C":"Group 8","W":988,"Z":1137},{"C":"Group 9","W":798,"Z":783},{"C":"Group 10","W":1263,"Z":1167},{"C":"Group 11","W":1566,"Z":1366},{"C":"Group 12","W":745,"Z":584},{"C":"Group 13","W":9031,"Z":9091},{"C":"Group 14","W":395,"Z":476},{"C":"Group 15","W":1266,"Z":1760},{"C":"Group 16","W":1881,"Z":1914},{"C":"Group 17","W":11836,"Z":14735},{"C":"Group 18","W":2204,"Z":2307},{"C":"Group 0","W":306,"Z":300},{"C":"Group 1","W":161,"Z":128},{"C":"Group 2","W":76,"Z":81},{"C":"Group 3","W":7241,"Z":6563},{"C":"Group 4","W":18485,"Z":14103},{"C":"Group 5","W":3906,"Z":3912},{"C":"Group 6","W":12633,"Z":13287},{"C":"Group 7","W":4873,"Z":5435},{"C":"Group 8","W":1358,"Z":1577},{"C":"Group 9","W":1572,"Z":1673},{"C":"Group 10","W":1239,"Z":1355},{"C":"Group 11","W":2565,"Z":2200},{"C":"Group 12","W":752,"Z":696},{"C":"Group 13","W":8387,"Z":9515},{"C":"Group 14","W":502,"Z":526},{"C":"Group 15","W":2041,"Z":2268},{"C":"Group 16","W":1435,"Z":1540},{"C":"Group 17","W":9266,"Z":11551},{"C":"Group 18","W":2272,"Z":2380},{"C":"Group 0","W":1483,"Z":1223},{"C":"Group 1","W":795,"Z":637},{"C":"Group 2","W":514,"Z":443},{"C":"Group 3","W":29562,"Z":24555},{"C":"Group 4","W":86709,"Z":67471},{"C":"Group 5","W":20615,"Z":20575},{"C":"Group 6","W":39298,"Z":35190},{"C":"Group 7","W":24092,"Z":23431},{"C":"Group 8","W":6488,"Z":7508},{"C":"Group 9","W":8762,"Z":8833},{"C":"Group 10","W":4884,"Z":4572},{"C":"Group 11","W":12804,"Z":12536},{"C":"Group 12","W":2832,"Z":2749},{"C":"Group 13","W":25710,"Z":27237},{"C":"Group 14","W":2378,"Z":2669},{"C":"Group 15","W":11249,"Z":11734},{"C":"Group 16","W":3947,"Z":3815},{"C":"Group 17","W":21829,"Z":23207},{"C":"Group 18","W":8410,"Z":7867},{"C":"Group 0","W":1672,"Z":1371},{"C":"Group 1","W":1311,"Z":954},{"C":"Group 2","W":749,"Z":705},{"C":"Group 3","W":30357,"Z":26818},{"C":"Group 4","W":94190,"Z":83994},{"C":"Group 5","W":22530,"Z":24300},{"C":"Group 6","W":34262,"Z":31879},{"C":"Group 7","W":27046,"Z":29286},{"C":"Group 8","W":6479,"Z":6754},{"C":"Group 9","W":7559,"Z":7945},{"C":"Group 10","W":4511,"Z":4242},{"C":"Group 11","W":12656,"Z":12551},{"C":"Group 12","W":2735,"Z":2823},{"C":"Group 13","W":21965,"Z":24569},{"C":"Group 14","W":2557,"Z":2791},{"C":"Group 15","W":13001,"Z":13407},{"C":"Group 16","W":3291,"Z":3253},{"C":"Group 17","W":13271,"Z":15510},{"C":"Group 18","W":8385,"Z":8191},{"C":"Group 0","W":1167,"Z":1066},{"C":"Group 1","W":1202,"Z":1137},{"C":"Group 2","W":754,"Z":802},{"C":"Group 3","W":18945,"Z":19932},{"C":"Group 4","W":72415,"Z":73514},{"C":"Group 5","W":16141,"Z":19282},{"C":"Group 6","W":23692,"Z":24842},{"C":"Group 7","W":20310,"Z":24676},{"C":"Group 8","W":5868,"Z":5789},{"C":"Group 9","W":6356,"Z":6415},{"C":"Group 10","W":2981,"Z":3260},{"C":"Group 11","W":9454,"Z":10971},{"C":"Group 12","W":1934,"Z":2336},{"C":"Group 13","W":13374,"Z":18000},{"C":"Group 14","W":2203,"Z":2696},{"C":"Group 15","W":9565,"Z":11847},{"C":"Group 16","W":2018,"Z":2449},{"C":"Group 17","W":6207,"Z":8180},{"C":"Group 18","W":6312,"Z":6995},{"C":"Group 0","W":539,"Z":594},{"C":"Group 1","W":588,"Z":572},{"C":"Group 2","W":360,"Z":448},{"C":"Group 3","W":9084,"Z":9490},{"C":"Group 4","W":34705,"Z":36295},{"C":"Group 5","W":7988,"Z":9997},{"C":"Group 6","W":12510,"Z":13785},{"C":"Group 7","W":9506,"Z":12134},{"C":"Group 8","W":2187,"Z":2565},{"C":"Group 9","W":2971,"Z":3625},{"C":"Group 10","W":1561,"Z":1787},{"C":"Group 11","W":4259,"Z":5691},{"C":"Group 12","W":966,"Z":1203},{"C":"Group 13","W":6349,"Z":9025},{"C":"Group 14","W":1402,"Z":1847},{"C":"Group 15","W":4061,"Z":5412},{"C":"Group 16","W":1162,"Z":1526},{"C":"Group 17","W":2562,"Z":3352},{"C":"Group 18","W":3167,"Z":3734},{"C":"Group 0","W":198,"Z":294},{"C":"Group 1","W":95,"Z":84},{"C":"Group 2","W":22,"Z":38},{"C":"Group 3","W":2072,"Z":2388},{"C":"Group 4","W":3997,"Z":4439},{"C":"Group 5","W":2201,"Z":2711},{"C":"Group 6","W":5635,"Z":6052},{"C":"Group 7","W":1400,"Z":2095},{"C":"Group 8","W":527,"Z":545},{"C":"Group 9","W":799,"Z":860},{"C":"Group 10","W":983,"Z":997},{"C":"Group 11","W":988,"Z":1296},{"C":"Group 12","W":279,"Z":336},{"C":"Group 13","W":2843,"Z":3823},{"C":"Group 14","W":435,"Z":563},{"C":"Group 15","W":1379,"Z":1710},{"C":"Group 16","W":679,"Z":1027},{"C":"Group 17","W":1185,"Z":1606},{"C":"Group 18","W":1538,"Z":1735},{"C":"Group 0","W":101,"Z":78},{"C":"Group 1","W":6,"Z":4},{"C":"Group 2","W":4,"Z":4},{"C":"Group 3","W":548,"Z":509},{"C":"Group 4","W":1522,"Z":957},{"C":"Group 5","W":515,"Z":489},{"C":"Group 6","W":14896,"Z":12053},{"C":"Group 7","W":219,"Z":216},{"C":"Group 8","W":782,"Z":635},{"C":"Group 9","W":596,"Z":410},{"C":"Group 10","W":800,"Z":530},{"C":"Group 11","W":954,"Z":882},{"C":"Group 12","W":633,"Z":357},{"C":"Group 13","W":2154,"Z":1974},{"C":"Group 14","W":430,"Z":400},{"C":"Group 15","W":2462,"Z":2523},{"C":"Group 16","W":2041,"Z":1865},{"C":"Group 17","W":19733,"Z":20103},{"C":"Group 18","W":1505,"Z":1579},{"C":"Group 0","W":87,"Z":81},{"C":"Group 1","W":15,"Z":11},{"C":"Group 2","W":14,"Z":17},{"C":"Group 3","W":797,"Z":778},{"C":"Group 4","W":6552,"Z":4010},{"C":"Group 5","W":1481,"Z":1321},{"C":"Group 6","W":18958,"Z":19106},{"C":"Group 7","W":1173,"Z":1301},{"C":"Group 8","W":1042,"Z":1044},{"C":"Group 9","W":3354,"Z":2876},{"C":"Group 10","W":1282,"Z":1180},{"C":"Group 11","W":2025,"Z":2188},{"C":"Group 12","W":745,"Z":798},{"C":"Group 13","W":7852,"Z":6780},{"C":"Group 14","W":696,"Z":797},{"C":"Group 15","W":7469,"Z":8860},{"C":"Group 16","W":1567,"Z":1622},{"C":"Group 17","W":16850,"Z":19756},{"C":"Group 18","W":2365,"Z":2617},{"C":"Group 0","W":78,"Z":82},{"C":"Group 1","W":13,"Z":10},{"C":"Group 2","W":21,"Z":10},{"C":"Group 3","W":1004,"Z":919},{"C":"Group 4","W":8501,"Z":6120},{"C":"Group 5","W":2095,"Z":2177},{"C":"Group 6","W":13702,"Z":14378},{"C":"Group 7","W":1770,"Z":2048},{"C":"Group 8","W":1451,"Z":1685},{"C":"Group 9","W":5259,"Z":5167},{"C":"Group 10","W":1325,"Z":1289},{"C":"Group 11","W":3014,"Z":3315},{"C":"Group 12","W":824,"Z":954},{"C":"Group 13","W":7808,"Z":7332},{"C":"Group 14","W":886,"Z":1106},{"C":"Group 15","W":11364,"Z":12913},{"C":"Group 16","W":1077,"Z":1236},{"C":"Group 17","W":11211,"Z":13637},{"C":"Group 18","W":2374,"Z":2449},{"C":"Group 0","W":395,"Z":376},{"C":"Group 1","W":100,"Z":53},{"C":"Group 2","W":169,"Z":142},{"C":"Group 3","W":3909,"Z":3544},{"C":"Group 4","W":43015,"Z":29440},{"C":"Group 5","W":10225,"Z":10059},{"C":"Group 6","W":37570,"Z":31942},{"C":"Group 7","W":8858,"Z":8201},{"C":"Group 8","W":6083,"Z":6742},{"C":"Group 9","W":20542,"Z":19277},{"C":"Group 10","W":4350,"Z":3929},{"C":"Group 11","W":13042,"Z":13162},{"C":"Group 12","W":3021,"Z":3269},{"C":"Group 13","W":23008,"Z":21483},{"C":"Group 14","W":3612,"Z":4235},{"C":"Group 15","W":51922,"Z":54349},{"C":"Group 16","W":2800,"Z":2580},{"C":"Group 17","W":25692,"Z":25044},{"C":"Group 18","W":8452,"Z":7666},{"C":"Group 0","W":444,"Z":400},{"C":"Group 1","W":145,"Z":103},{"C":"Group 2","W":262,"Z":281},{"C":"Group 3","W":4339,"Z":4408},{"C":"Group 4","W":52884,"Z":42740},{"C":"Group 5","W":10740,"Z":12026},{"C":"Group 6","W":36373,"Z":33852},{"C":"Group 7","W":9728,"Z":11049},{"C":"Group 8","W":6213,"Z":6180},{"C":"Group 9","W":18578,"Z":18345},{"C":"Group 10","W":3915,"Z":3775},{"C":"Group 11","W":12469,"Z":13303},{"C":"Group 12","W":3108,"Z":3571},{"C":"Group 13","W":18899,"Z":20442},{"C":"Group 14","W":4139,"Z":4445},{"C":"Group 15","W":55175,"Z":56479},{"C":"Group 16","W":2403,"Z":2338},{"C":"Group 17","W":20741,"Z":21451},{"C":"Group 18","W":8693,"Z":8455},{"C":"Group 0","W":358,"Z":393},{"C":"Group 1","W":111,"Z":93},{"C":"Group 2","W":234,"Z":266},{"C":"Group 3","W":3216,"Z":3598},{"C":"Group 4","W":41394,"Z":38821},{"C":"Group 5","W":7450,"Z":9263},{"C":"Group 6","W":28040,"Z":29686},{"C":"Group 7","W":5936,"Z":8616},{"C":"Group 8","W":5150,"Z":5415},{"C":"Group 9","W":13515,"Z":15182},{"C":"Group 10","W":2936,"Z":3073},{"C":"Group 11","W":8387,"Z":10740},{"C":"Group 12","W":2083,"Z":3181},{"C":"Group 13","W":11613,"Z":15344},{"C":"Group 14","W":3974,"Z":4690},{"C":"Group 15","W":38382,"Z":48697},{"C":"Group 16","W":1625,"Z":1960},{"C":"Group 17","W":11512,"Z":13389},{"C":"Group 18","W":7113,"Z":7455},{"C":"Group 0","W":183,"Z":205},{"C":"Group 1","W":46,"Z":45},{"C":"Group 2","W":122,"Z":124},{"C":"Group 3","W":1660,"Z":1976},{"C":"Group 4","W":19533,"Z":19218},{"C":"Group 5","W":3177,"Z":4165},{"C":"Group 6","W":15999,"Z":17533},{"C":"Group 7","W":1902,"Z":2998},{"C":"Group 8","W":1653,"Z":1865},{"C":"Group 9","W":5345,"Z":6776},{"C":"Group 10","W":1580,"Z":1804},{"C":"Group 11","W":2910,"Z":4408},{"C":"Group 12","W":856,"Z":1577},{"C":"Group 13","W":4540,"Z":6496},{"C":"Group 14","W":1637,"Z":2441},{"C":"Group 15","W":16300,"Z":21180},{"C":"Group 16","W":954,"Z":1195},{"C":"Group 17","W":5505,"Z":6240},{"C":"Group 18","W":4340,"Z":4578},{"C":"Group 0","W":110,"Z":129},{"C":"Group 1","W":13,"Z":12},{"C":"Group 2","W":8,"Z":15},{"C":"Group 3","W":709,"Z":869},{"C":"Group 4","W":3049,"Z":2987},{"C":"Group 5","W":866,"Z":1069},{"C":"Group 6","W":6676,"Z":7237},{"C":"Group 7","W":283,"Z":468},{"C":"Group 8","W":385,"Z":368},{"C":"Group 9","W":916,"Z":1076},{"C":"Group 10","W":645,"Z":751},{"C":"Group 11","W":802,"Z":975},{"C":"Group 12","W":210,"Z":311},{"C":"Group 13","W":1387,"Z":2389},{"C":"Group 14","W":391,"Z":482},{"C":"Group 15","W":3750,"Z":4817},{"C":"Group 16","W":435,"Z":601},{"C":"Group 17","W":2220,"Z":2700},{"C":"Group 18","W":2272,"Z":2177}]