[{"C":"Group 2","W":50.981,"Z":51.204},{"C":"Group 2","W":49.892,"Z":49.98},{"C":"Group 2","W":49.689,"Z":49.816},{"C":"Group 2","W":49.816,"Z":49.892},{"C":"Group 2","W":29.118,"Z":29.392},{"C":"Group 2","W":61.371,"Z":61.474},{"C":"Group 2","W":51.28,"Z":51.367},{"C":"Group 7","W":6.259,"Z":6.338},{"C":"Group 2","W":40.343,"Z":40.543},{"C":"Group 5","W":11.799,"Z":11.868},{"C":"Group 2","W":40.543,"Z":40.605},{"C":"Group 10","W":1.293,"Z":1.337},{"C":"Group 9","W":2.395,"Z":2.425},{"C":"Group 9","W":2.357,"Z":2.371},{"C":"Group 2","W":51.367,"Z":51.44},{"C":"Group 9","W":2.271,"Z":2.301},{"C":"Group 8","W":4.895,"Z":5.003},{"C":"Group 2","W":50.462,"Z":50.509},{"C":"Group 9","W":1.355,"Z":1.518},{"C":"Group 9","W":2.168,"Z":2.271},{"C":"Group 1","W":8.85,"Z":9.067},{"C":"Group 9","W":2.092,"Z":2.131},{"C":"Group 9","W":1.854,"Z":2.003},{"C":"Group 2","W":61.474,"Z":61.548},{"C":"Group 3","W":1.186,"Z":1.405},{"C":"Group 3","W":1.186,"Z":1.405},{"C":"Group 2","W":51.567,"Z":51.701},{"C":"Group 6","W":22.029,"Z":22.191},{"C":"Group 2","W":61.772,"Z":61.908},{"C":"Group 6","W":22.392,"Z":22.605},{"C":"Group 9","W":2.048,"Z":2.092},{"C":"Group 9","W":1.518,"Z":1.706},{"C":"Group 2","W":60.977,"Z":61.371},{"C":"Group 9","W":1.706,"Z":1.764},{"C":"Group 4","W":26.629,"Z":27.783},{"C":"Group 2","W":50.721,"Z":50.82},{"C":"Group 0","W":17.134,"Z":17.917},{"C":"Group 9","W":1.21,"Z":1.248},{"C":"Group 2","W":50.616,"Z":50.721},{"C":"Group 9","W":1.034,"Z":1.172},{"C":"Group 9","W":2.431,"Z":2.47},{"C":"Group 9","W":2.47,"Z":2.537},{"C":"Group 9","W":2.537,"Z":2.585},{"C":"Group 2","W":61.548,"Z":61.772},{"C":"Group 9","W":6.413,"Z":7.843},{"C":"Group 9","W":1.248,"Z":1.355},{"C":"Group 2","W":61.908,"Z":62.131}]