[{"C":"Group 0","W":1,"Z":0.0},{"C":"Group 4","W":4,"Z":5.92},{"C":"Group 3","W":0,"Z":4.24},{"C":"Group 5","W":7,"Z":0.0},{"C":"Group 3","W":5,"Z":4.65},{"C":"Group 1","W":0,"Z":3.6},{"C":"Group 2","W":5,"Z":3.49},{"C":"Group 3","W":10,"Z":5.07},{"C":"Group 2","W":10,"Z":3.89},{"C":"Group 3","W":26,"Z":3.95},{"C":"Group 3","W":30,"Z":4.03},{"C":"Group 0","W":3,"Z":3.34},{"C":"Group 3","W":21,"Z":4.14},{"C":"Group 0","W":2,"Z":2.97},{"C":"Group 1","W":3,"Z":4.69},{"C":"Group 3","W":10,"Z":5.48},{"C":"Group 0","W":1,"Z":13.84},{"C":"Group 3","W":6,"Z":4.46},{"C":"Group 0","W":0,"Z":2.78},{"C":"Group 2","W":0,"Z":3.86},{"C":"Group 3","W":5,"Z":3.95},{"C":"Group 1","W":2,"Z":3.72},{"C":"Group 2","W":1,"Z":5.03}]