[{"C":"Group 2","W":2.25,"Z":51},{"C":"Group 1","W":3.43,"Z":1},{"C":"Group 0","W":3.2,"Z":1},{"C":"Group 0","W":3.76,"Z":1},{"C":"Group 2","W":3.85,"Z":26},{"C":"Group 2","W":4.58,"Z":25},{"C":"Group 0","W":4.4,"Z":1},{"C":"Group 2","W":4.52,"Z":37},{"C":"Group 2","W":3.45,"Z":12},{"C":"Group 2","W":3.61,"Z":54},{"C":"Group 2","W":4.05,"Z":153},{"C":"Group 2","W":4.09,"Z":291},{"C":"Group 2","W":3.42,"Z":24},{"C":"Group 2","W":4.23,"Z":13},{"C":"Group 1","W":4.08,"Z":6},{"C":"Group 2","W":4.45,"Z":51},{"C":"Group 0","W":4.14,"Z":1},{"C":"Group 2","W":4.21,"Z":24},{"C":"Group 2","W":4.39,"Z":12},{"C":"Group 0","W":4.27,"Z":1},{"C":"Group 0","W":4.27,"Z":1},{"C":"Group 1","W":4.29,"Z":1},{"C":"Group 1","W":4.14,"Z":6},{"C":"Group 2","W":2.87,"Z":12},{"C":"Group 2","W":4.06,"Z":13},{"C":"Group 0","W":4.53,"Z":1},{"C":"Group 4","W":2.56,"Z":4},{"C":"Group 2","W":3.61,"Z":24},{"C":"Group 2","W":4.07,"Z":24},{"C":"Group 3","W":3.77,"Z":1},{"C":"Group 3","W":3.68,"Z":1},{"C":"Group 2","W":3.85,"Z":45},{"C":"Group 2","W":4.5,"Z":26},{"C":"Group 2","W":3.88,"Z":220},{"C":"Group 2","W":4.18,"Z":26},{"C":"Group 0","W":3.68,"Z":1},{"C":"Group 0","W":4.15,"Z":1},{"C":"Group 0","W":3.79,"Z":1},{"C":"Group 0","W":3.79,"Z":1},{"C":"Group 2","W":3.75,"Z":13},{"C":"Group 0","W":4.54,"Z":1},{"C":"Group 2","W":3.23,"Z":46},{"C":"Group 2","W":3.73,"Z":114},{"C":"Group 2","W":4.41,"Z":26},{"C":"Group 2","W":2.96,"Z":54},{"C":"Group 2","W":3.9,"Z":13},{"C":"Group 2","W":3.47,"Z":48},{"C":"Group 2","W":4.28,"Z":51},{"C":"Group 0","W":4.56,"Z":1},{"C":"Group 0","W":3.26,"Z":1}]