[{"C":"Group 0","W":63,"Z":1.9881},{"C":"Group 1","W":91,"Z":2.1722},{"C":"Group 15","W":31,"Z":2.2204},{"C":"Group 1","W":59,"Z":2.2458},{"C":"Group 24","W":154,"Z":2.2473},{"C":"Group 18","W":126,"Z":2.3082},{"C":"Group 18","W":165,"Z":2.3659},{"C":"Group 13","W":119,"Z":2.3764},{"C":"Group 0","W":223,"Z":2.4083},{"C":"Group 14","W":49,"Z":2.4354},{"C":"Group 18","W":135,"Z":2.442},{"C":"Group 25","W":136,"Z":2.4559},{"C":"Group 24","W":133,"Z":2.4699},{"C":"Group 12","W":170,"Z":2.5212},{"C":"Group 19","W":78,"Z":2.5214},{"C":"Group 11","W":34,"Z":2.5294},{"C":"Group 10","W":60,"Z":2.5333},{"C":"Group 4","W":112,"Z":2.5405},{"C":"Group 25","W":97,"Z":2.5481},{"C":"Group 13","W":148,"Z":2.5484},{"C":"Group 2","W":84,"Z":2.5703},{"C":"Group 8","W":69,"Z":2.5966},{"C":"Group 23","W":62,"Z":2.6093},{"C":"Group 21","W":69,"Z":2.6127},{"C":"Group 8","W":33,"Z":2.6263},{"C":"Group 3","W":88,"Z":2.6264},{"C":"Group 3","W":150,"Z":2.6356},{"C":"Group 11","W":52,"Z":2.6709},{"C":"Group 13","W":94,"Z":2.6756},{"C":"Group 8","W":111,"Z":2.6832},{"C":"Group 12","W":117,"Z":2.688},{"C":"Group 8","W":271,"Z":2.708},{"C":"Group 8","W":80,"Z":2.7125},{"C":"Group 2","W":45,"Z":2.7159},{"C":"Group 23","W":171,"Z":2.7173},{"C":"Group 7","W":188,"Z":2.7216},{"C":"Group 12","W":115,"Z":2.7249},{"C":"Group 5","W":35,"Z":2.7623},{"C":"Group 21","W":54,"Z":2.7642},{"C":"Group 12","W":143,"Z":2.7734},{"C":"Group 16","W":136,"Z":2.7745},{"C":"Group 16","W":90,"Z":2.7772},{"C":"Group 26","W":46,"Z":2.7781},{"C":"Group 8","W":50,"Z":2.7823},{"C":"Group 0","W":42,"Z":2.7857},{"C":"Group 8","W":73,"Z":2.7877},{"C":"Group 1","W":228,"Z":2.7884},{"C":"Group 14","W":153,"Z":2.793},{"C":"Group 8","W":140,"Z":2.8003},{"C":"Group 1","W":164,"Z":2.8039},{"C":"Group 5","W":216,"Z":2.8043},{"C":"Group 16","W":158,"Z":2.8066},{"C":"Group 16","W":108,"Z":2.8102},{"C":"Group 25","W":113,"Z":2.823},{"C":"Group 13","W":78,"Z":2.8299},{"C":"Group 8","W":50,"Z":2.8308},{"C":"Group 19","W":102,"Z":2.8317},{"C":"Group 5","W":56,"Z":2.8398},{"C":"Group 8","W":51,"Z":2.8497},{"C":"Group 15","W":88,"Z":2.8506},{"C":"Group 6","W":67,"Z":2.8535},{"C":"Group 23","W":97,"Z":2.8643},{"C":"Group 5","W":183,"Z":2.8649},{"C":"Group 16","W":115,"Z":2.8681},{"C":"Group 20","W":42,"Z":2.869},{"C":"Group 0","W":32,"Z":2.8802},{"C":"Group 20","W":120,"Z":2.8819},{"C":"Group 1","W":204,"Z":2.8857},{"C":"Group 13","W":252,"Z":2.8884},{"C":"Group 8","W":78,"Z":2.891},{"C":"Group 4","W":44,"Z":2.8939},{"C":"Group 7","W":86,"Z":2.9031},{"C":"Group 4","W":94,"Z":2.9113},{"C":"Group 12","W":207,"Z":2.9114},{"C":"Group 14","W":91,"Z":2.9121},{"C":"Group 15","W":57,"Z":2.9144},{"C":"Group 1","W":39,"Z":2.9158},{"C":"Group 8","W":133,"Z":2.9223},{"C":"Group 20","W":218,"Z":2.9264},{"C":"Group 3","W":83,"Z":2.9277},{"C":"Group 0","W":52,"Z":2.9305},{"C":"Group 2","W":43,"Z":2.938},{"C":"Group 12","W":144,"Z":2.9477},{"C":"Group 6","W":98,"Z":2.949},{"C":"Group 4","W":312,"Z":2.953},{"C":"Group 13","W":247,"Z":2.9593},{"C":"Group 24","W":104,"Z":2.9602},{"C":"Group 10","W":39,"Z":2.9658},{"C":"Group 5","W":156,"Z":2.9733},{"C":"Group 7","W":246,"Z":2.9743},{"C":"Group 2","W":61,"Z":2.9781},{"C":"Group 18","W":57,"Z":2.9795},{"C":"Group 0","W":94,"Z":2.983},{"C":"Group 9","W":208,"Z":2.9837},{"C":"Group 5","W":153,"Z":2.9956},{"C":"Group 12","W":209,"Z":3.0033},{"C":"Group 5","W":50,"Z":3.0033},{"C":"Group 4","W":180,"Z":3.0047},{"C":"Group 11","W":292,"Z":3.0057},{"C":"Group 21","W":76,"Z":3.0066},{"C":"Group 9","W":79,"Z":3.0107},{"C":"Group 12","W":52,"Z":3.0123},{"C":"Group 5","W":169,"Z":3.0148},{"C":"Group 20","W":109,"Z":3.0159},{"C":"Group 14","W":33,"Z":3.0172},{"C":"Group 1","W":469,"Z":3.018},{"C":"Group 8","W":58,"Z":3.0259},{"C":"Group 11","W":167,"Z":3.0259},{"C":"Group 13","W":331,"Z":3.0263},{"C":"Group 4","W":127,"Z":3.0265},{"C":"Group 10","W":63,"Z":3.0278},{"C":"Group 4","W":31,"Z":3.0281},{"C":"Group 8","W":54,"Z":3.0309},{"C":"Group 7","W":32,"Z":3.0312},{"C":"Group 12","W":195,"Z":3.0329},{"C":"Group 23","W":57,"Z":3.0335},{"C":"Group 20","W":100,"Z":3.0417},{"C":"Group 7","W":67,"Z":3.044},{"C":"Group 12","W":33,"Z":3.0472},{"C":"Group 8","W":81,"Z":3.0528},{"C":"Group 4","W":100,"Z":3.0533},{"C":"Group 5","W":34,"Z":3.0588},{"C":"Group 4","W":219,"Z":3.0601},{"C":"Group 10","W":255,"Z":3.0608},{"C":"Group 21","W":120,"Z":3.0639},{"C":"Group 3","W":284,"Z":3.0661},{"C":"Group 25","W":70,"Z":3.069},{"C":"Group 8","W":96,"Z":3.0752},{"C":"Group 0","W":107,"Z":3.0758},{"C":"Group 23","W":46,"Z":3.0761},{"C":"Group 8","W":397,"Z":3.0785},{"C":"Group 11","W":80,"Z":3.0833},{"C":"Group 20","W":130,"Z":3.0885},{"C":"Group 4","W":225,"Z":3.0997},{"C":"Group 20","W":35,"Z":3.1},{"C":"Group 4","W":163,"Z":3.107},{"C":"Group 13","W":31,"Z":3.1075},{"C":"Group 25","W":268,"Z":3.1135},{"C":"Group 18","W":63,"Z":3.1164},{"C":"Group 2","W":50,"Z":3.1187},{"C":"Group 8","W":43,"Z":3.1196},{"C":"Group 3","W":32,"Z":3.1198},{"C":"Group 8","W":288,"Z":3.1227},{"C":"Group 12","W":127,"Z":3.1234},{"C":"Group 24","W":81,"Z":3.1235},{"C":"Group 7","W":184,"Z":3.1248},{"C":"Group 0","W":131,"Z":3.1279},{"C":"Group 15","W":34,"Z":3.1346},{"C":"Group 19","W":41,"Z":3.1357},{"C":"Group 12","W":120,"Z":3.1361},{"C":"Group 1","W":110,"Z":3.1364},{"C":"Group 8","W":390,"Z":3.141},{"C":"Group 11","W":43,"Z":3.1454},{"C":"Group 24","W":31,"Z":3.1457},{"C":"Group 6","W":34,"Z":3.1471},{"C":"Group 0","W":31,"Z":3.1503},{"C":"Group 4","W":266,"Z":3.1552},{"C":"Group 26","W":49,"Z":3.1567},{"C":"Group 12","W":166,"Z":3.157},{"C":"Group 12","W":410,"Z":3.1582},{"C":"Group 8","W":37,"Z":3.1678},{"C":"Group 15","W":389,"Z":3.1684},{"C":"Group 12","W":173,"Z":3.1696},{"C":"Group 20","W":51,"Z":3.1699},{"C":"Group 14","W":155,"Z":3.1722},{"C":"Group 9","W":108,"Z":3.1727},{"C":"Group 12","W":178,"Z":3.1751},{"C":"Group 7","W":210,"Z":3.1774},{"C":"Group 0","W":76,"Z":3.18},{"C":"Group 8","W":49,"Z":3.1837},{"C":"Group 18","W":232,"Z":3.1899},{"C":"Group 0","W":70,"Z":3.1976},{"C":"Group 25","W":68,"Z":3.1991},{"C":"Group 1","W":158,"Z":3.2057},{"C":"Group 2","W":140,"Z":3.2111},{"C":"Group 4","W":45,"Z":3.2185},{"C":"Group 25","W":60,"Z":3.2191},{"C":"Group 11","W":42,"Z":3.2195},{"C":"Group 6","W":32,"Z":3.2204},{"C":"Group 23","W":56,"Z":3.2228},{"C":"Group 18","W":57,"Z":3.2233},{"C":"Group 8","W":398,"Z":3.2284},{"C":"Group 11","W":57,"Z":3.2303},{"C":"Group 8","W":33,"Z":3.2331},{"C":"Group 12","W":441,"Z":3.2349},{"C":"Group 16","W":31,"Z":3.2361},{"C":"Group 2","W":152,"Z":3.2365},{"C":"Group 7","W":80,"Z":3.2441},{"C":"Group 15","W":404,"Z":3.2454},{"C":"Group 4","W":51,"Z":3.2505},{"C":"Group 20","W":196,"Z":3.2548},{"C":"Group 15","W":47,"Z":3.2551},{"C":"Group 11","W":82,"Z":3.2673},{"C":"Group 1","W":55,"Z":3.27},{"C":"Group 8","W":137,"Z":3.2788},{"C":"Group 1","W":206,"Z":3.2791},{"C":"Group 24","W":72,"Z":3.2923},{"C":"Group 5","W":293,"Z":3.2993},{"C":"Group 13","W":30,"Z":3.3007},{"C":"Group 15","W":88,"Z":3.3013},{"C":"Group 13","W":248,"Z":3.3019},{"C":"Group 0","W":143,"Z":3.3031},{"C":"Group 1","W":95,"Z":3.3048},{"C":"Group 0","W":150,"Z":3.3056},{"C":"Group 2","W":427,"Z":3.3067},{"C":"Group 13","W":40,"Z":3.3083},{"C":"Group 25","W":165,"Z":3.309},{"C":"Group 0","W":292,"Z":3.3102},{"C":"Group 8","W":35,"Z":3.3115},{"C":"Group 1","W":31,"Z":3.313},{"C":"Group 26","W":46,"Z":3.3155},{"C":"Group 12","W":224,"Z":3.3155},{"C":"Group 24","W":394,"Z":3.3211},{"C":"Group 5","W":47,"Z":3.3267},{"C":"Group 0","W":32,"Z":3.3281},{"C":"Group 8","W":35,"Z":3.3333},{"C":"Group 15","W":293,"Z":3.3336},{"C":"Group 20","W":104,"Z":3.3344},{"C":"Group 20","W":330,"Z":3.3354},{"C":"Group 8","W":38,"Z":3.3377},{"C":"Group 14","W":553,"Z":3.3407},{"C":"Group 22","W":34,"Z":3.3438},{"C":"Group 5","W":146,"Z":3.3465},{"C":"Group 15","W":110,"Z":3.3545},{"C":"Group 15","W":132,"Z":3.3548},{"C":"Group 19","W":168,"Z":3.3564},{"C":"Group 1","W":453,"Z":3.3565},{"C":"Group 8","W":72,"Z":3.3585},{"C":"Group 8","W":196,"Z":3.3614},{"C":"Group 0","W":33,"Z":3.3636},{"C":"Group 13","W":62,"Z":3.3644},{"C":"Group 10","W":51,"Z":3.366},{"C":"Group 1","W":53,"Z":3.3665},{"C":"Group 1","W":66,"Z":3.3674},{"C":"Group 12","W":335,"Z":3.3689},{"C":"Group 1","W":226,"Z":3.3699},{"C":"Group 8","W":83,"Z":3.3715},{"C":"Group 23","W":500,"Z":3.3751},{"C":"Group 2","W":104,"Z":3.383},{"C":"Group 15","W":174,"Z":3.3834},{"C":"Group 0","W":433,"Z":3.3841},{"C":"Group 8","W":459,"Z":3.3863},{"C":"Group 19","W":74,"Z":3.3898},{"C":"Group 26","W":40,"Z":3.3946},{"C":"Group 4","W":424,"Z":3.3961},{"C":"Group 15","W":64,"Z":3.3966},{"C":"Group 16","W":30,"Z":3.3967},{"C":"Group 6","W":314,"Z":3.4036},{"C":"Group 12","W":191,"Z":3.4065},{"C":"Group 21","W":45,"Z":3.4122},{"C":"Group 16","W":111,"Z":3.4127},{"C":"Group 0","W":45,"Z":3.4148},{"C":"Group 8","W":127,"Z":3.4166},{"C":"Group 0","W":57,"Z":3.4167},{"C":"Group 15","W":445,"Z":3.4169},{"C":"Group 15","W":33,"Z":3.4192},{"C":"Group 20","W":505,"Z":3.4225},{"C":"Group 3","W":143,"Z":3.4269},{"C":"Group 12","W":200,"Z":3.4283},{"C":"Group 8","W":104,"Z":3.4295},{"C":"Group 13","W":132,"Z":3.4313},{"C":"Group 4","W":233,"Z":3.4328},{"C":"Group 1","W":291,"Z":3.4333},{"C":"Group 12","W":70,"Z":3.4345},{"C":"Group 1","W":170,"Z":3.4345},{"C":"Group 8","W":386,"Z":3.4365},{"C":"Group 1","W":81,"Z":3.4384},{"C":"Group 15","W":36,"Z":3.4387},{"C":"Group 1","W":167,"Z":3.4423},{"C":"Group 8","W":109,"Z":3.4462},{"C":"Group 3","W":109,"Z":3.4475},{"C":"Group 8","W":55,"Z":3.4492},{"C":"Group 15","W":124,"Z":3.4495},{"C":"Group 10","W":113,"Z":3.4501},{"C":"Group 19","W":106,"Z":3.4508},{"C":"Group 0","W":55,"Z":3.4515},{"C":"Group 4","W":329,"Z":3.465},{"C":"Group 2","W":96,"Z":3.4653},{"C":"Group 14","W":86,"Z":3.4653},{"C":"Group 8","W":83,"Z":3.4654},{"C":"Group 18","W":130,"Z":3.4667},{"C":"Group 1","W":169,"Z":3.4686},{"C":"Group 16","W":177,"Z":3.4697},{"C":"Group 13","W":37,"Z":3.473},{"C":"Group 11","W":172,"Z":3.4845},{"C":"Group 18","W":418,"Z":3.4872},{"C":"Group 5","W":427,"Z":3.4929},{"C":"Group 25","W":121,"Z":3.4972},{"C":"Group 20","W":376,"Z":3.4973},{"C":"Group 0","W":62,"Z":3.5031},{"C":"Group 8","W":273,"Z":3.5055},{"C":"Group 12","W":248,"Z":3.5102},{"C":"Group 4","W":76,"Z":3.5135},{"C":"Group 0","W":111,"Z":3.5182},{"C":"Group 12","W":141,"Z":3.525},{"C":"Group 5","W":318,"Z":3.5308},{"C":"Group 12","W":198,"Z":3.5372},{"C":"Group 12","W":600,"Z":3.5384},{"C":"Group 13","W":379,"Z":3.5467},{"C":"Group 20","W":39,"Z":3.5537},{"C":"Group 11","W":294,"Z":3.5575},{"C":"Group 17","W":67,"Z":3.5605},{"C":"Group 5","W":44,"Z":3.5609},{"C":"Group 16","W":500,"Z":3.565},{"C":"Group 23","W":99,"Z":3.5697},{"C":"Group 20","W":162,"Z":3.5698},{"C":"Group 2","W":153,"Z":3.5718},{"C":"Group 5","W":334,"Z":3.5783},{"C":"Group 22","W":180,"Z":3.5796},{"C":"Group 15","W":166,"Z":3.5799},{"C":"Group 7","W":128,"Z":3.5833},{"C":"Group 16","W":149,"Z":3.5846},{"C":"Group 4","W":457,"Z":3.5865},{"C":"Group 1","W":395,"Z":3.5906},{"C":"Group 24","W":147,"Z":3.5912},{"C":"Group 8","W":33,"Z":3.5921},{"C":"Group 14","W":198,"Z":3.5927},{"C":"Group 0","W":102,"Z":3.5945},{"C":"Group 12","W":89,"Z":3.5951},{"C":"Group 15","W":316,"Z":3.5999},{"C":"Group 25","W":418,"Z":3.605},{"C":"Group 15","W":179,"Z":3.618},{"C":"Group 12","W":298,"Z":3.6205},{"C":"Group 15","W":452,"Z":3.6206},{"C":"Group 18","W":290,"Z":3.6231},{"C":"Group 18","W":408,"Z":3.6278},{"C":"Group 15","W":64,"Z":3.6302},{"C":"Group 1","W":378,"Z":3.6373},{"C":"Group 15","W":485,"Z":3.6453},{"C":"Group 11","W":207,"Z":3.6464},{"C":"Group 8","W":88,"Z":3.6531},{"C":"Group 1","W":50,"Z":3.6534},{"C":"Group 10","W":89,"Z":3.6536},{"C":"Group 5","W":75,"Z":3.6556},{"C":"Group 21","W":39,"Z":3.6579},{"C":"Group 12","W":466,"Z":3.6593},{"C":"Group 1","W":164,"Z":3.6628},{"C":"Group 8","W":421,"Z":3.6631},{"C":"Group 18","W":424,"Z":3.669},{"C":"Group 19","W":74,"Z":3.6804},{"C":"Group 4","W":152,"Z":3.6821},{"C":"Group 24","W":407,"Z":3.6942},{"C":"Group 2","W":47,"Z":3.695},{"C":"Group 26","W":135,"Z":3.6951},{"C":"Group 1","W":135,"Z":3.7029},{"C":"Group 8","W":202,"Z":3.7067},{"C":"Group 8","W":384,"Z":3.7074},{"C":"Group 20","W":69,"Z":3.7124},{"C":"Group 3","W":106,"Z":3.7127},{"C":"Group 26","W":62,"Z":3.7166},{"C":"Group 20","W":144,"Z":3.7168},{"C":"Group 1","W":327,"Z":3.7222},{"C":"Group 8","W":45,"Z":3.7311},{"C":"Group 5","W":36,"Z":3.7361},{"C":"Group 0","W":57,"Z":3.7412},{"C":"Group 9","W":192,"Z":3.7418},{"C":"Group 25","W":438,"Z":3.7449},{"C":"Group 8","W":258,"Z":3.7543},{"C":"Group 1","W":40,"Z":3.7653},{"C":"Group 22","W":189,"Z":3.7712},{"C":"Group 2","W":94,"Z":3.7713},{"C":"Group 4","W":44,"Z":3.7726},{"C":"Group 21","W":104,"Z":3.774},{"C":"Group 26","W":56,"Z":3.7821},{"C":"Group 24","W":200,"Z":3.7864},{"C":"Group 13","W":114,"Z":3.7868},{"C":"Group 0","W":31,"Z":3.7906},{"C":"Group 2","W":399,"Z":3.8012},{"C":"Group 8","W":48,"Z":3.8125},{"C":"Group 5","W":36,"Z":3.8177},{"C":"Group 15","W":94,"Z":3.8262},{"C":"Group 5","W":36,"Z":3.8403},{"C":"Group 22","W":295,"Z":3.8413},{"C":"Group 25","W":68,"Z":3.8421},{"C":"Group 17","W":33,"Z":3.8467},{"C":"Group 0","W":53,"Z":3.8501},{"C":"Group 0","W":248,"Z":3.8535},{"C":"Group 1","W":143,"Z":3.8548},{"C":"Group 25","W":158,"Z":3.8731},{"C":"Group 7","W":138,"Z":3.8917},{"C":"Group 8","W":852,"Z":3.8927},{"C":"Group 1","W":39,"Z":3.8955},{"C":"Group 20","W":381,"Z":3.8971},{"C":"Group 21","W":206,"Z":3.9102},{"C":"Group 18","W":138,"Z":3.9122},{"C":"Group 19","W":51,"Z":3.9281},{"C":"Group 15","W":41,"Z":3.9309},{"C":"Group 18","W":386,"Z":3.9356},{"C":"Group 8","W":83,"Z":3.947},{"C":"Group 0","W":30,"Z":3.95},{"C":"Group 26","W":75,"Z":3.9509},{"C":"Group 1","W":34,"Z":3.9565},{"C":"Group 12","W":344,"Z":3.9566},{"C":"Group 17","W":120,"Z":3.9608},{"C":"Group 1","W":100,"Z":3.9762},{"C":"Group 23","W":110,"Z":3.9799},{"C":"Group 12","W":138,"Z":3.9853},{"C":"Group 17","W":118,"Z":3.9936},{"C":"Group 11","W":142,"Z":3.9964},{"C":"Group 18","W":185,"Z":4.0027},{"C":"Group 17","W":43,"Z":4.0033},{"C":"Group 12","W":36,"Z":4.0119},{"C":"Group 17","W":42,"Z":4.0246},{"C":"Group 0","W":138,"Z":4.0338},{"C":"Group 4","W":456,"Z":4.0449},{"C":"Group 10","W":122,"Z":4.0494},{"C":"Group 25","W":84,"Z":4.0562},{"C":"Group 18","W":35,"Z":4.064},{"C":"Group 25","W":142,"Z":4.0719},{"C":"Group 26","W":161,"Z":4.0887},{"C":"Group 13","W":33,"Z":4.1023},{"C":"Group 22","W":117,"Z":4.1149},{"C":"Group 18","W":582,"Z":4.1158},{"C":"Group 26","W":137,"Z":4.132},{"C":"Group 1","W":235,"Z":4.1391},{"C":"Group 26","W":47,"Z":4.1631},{"C":"Group 0","W":65,"Z":4.1647},{"C":"Group 26","W":123,"Z":4.1874},{"C":"Group 26","W":46,"Z":4.2082},{"C":"Group 8","W":37,"Z":4.3018},{"C":"Group 26","W":178,"Z":4.3567},{"C":"Group 26","W":101,"Z":4.4617},{"C":"Group 26","W":100,"Z":4.6379}]