[{"C":"Group 0","W":5000,"Z":330},{"C":"Group 1","W":4620,"Z":210},{"C":"Group 2","W":2770,"Z":190},{"C":"Group 3","W":2610,"Z":140},{"C":"Group 4","W":4600,"Z":350},{"C":"Group 5","W":4840,"Z":360},{"C":"Group 6","W":2340,"Z":190},{"C":"Group 7","W":2740,"Z":250},{"C":"Group 8","W":2470,"Z":150},{"C":"Group 9","W":7720,"Z":580},{"C":"Group 10","W":7910,"Z":530},{"C":"Group 11","W":7380,"Z":690},{"C":"Group 12","W":2800,"Z":260},{"C":"Group 13","W":5600,"Z":380},{"C":"Group 14","W":5180,"Z":350},{"C":"Group 15","W":2400,"Z":140},{"C":"Group 16","W":6650,"Z":640},{"C":"Group 17","W":2570,"Z":240},{"C":"Group 18","W":2900,"Z":120},{"C":"Group 19","W":2550,"Z":130},{"C":"Group 20","W":2630,"Z":150},{"C":"Group 21","W":2750,"Z":150},{"C":"Group 22","W":5830,"Z":300},{"C":"Group 23","W":2360,"Z":200},{"C":"Group 0","W":6160,"Z":410},{"C":"Group 1","W":4690,"Z":240},{"C":"Group 2","W":2780,"Z":210},{"C":"Group 3","W":3060,"Z":170},{"C":"Group 4","W":4970,"Z":410},{"C":"Group 5","W":4910,"Z":400},{"C":"Group 6","W":2570,"Z":220},{"C":"Group 7","W":2720,"Z":280},{"C":"Group 8","W":2850,"Z":180},{"C":"Group 9","W":7730,"Z":660},{"C":"Group 10","W":7920,"Z":600},{"C":"Group 11","W":8910,"Z":820},{"C":"Group 12","W":3040,"Z":300},{"C":"Group 13","W":5670,"Z":430},{"C":"Group 14","W":5470,"Z":400},{"C":"Group 15","W":2890,"Z":180},{"C":"Group 16","W":6940,"Z":730},{"C":"Group 18","W":2910,"Z":130},{"C":"Group 17","W":2690,"Z":270},{"C":"Group 19","W":3160,"Z":170},{"C":"Group 20","W":3210,"Z":190},{"C":"Group 21","W":2840,"Z":170},{"C":"Group 22","W":5740,"Z":340},{"C":"Group 23","W":3800,"Z":280},{"C":"Group 0","W":6760,"Z":520},{"C":"Group 1","W":4570,"Z":290},{"C":"Group 2","W":2750,"Z":260},{"C":"Group 3","W":3330,"Z":220},{"C":"Group 4","W":4910,"Z":500},{"C":"Group 5","W":4810,"Z":490},{"C":"Group 6","W":2510,"Z":260},{"C":"Group 7","W":2700,"Z":340},{"C":"Group 8","W":2800,"Z":220},{"C":"Group 9","W":7600,"Z":790},{"C":"Group 10","W":7750,"Z":720},{"C":"Group 11","W":12090,"Z":1110},{"C":"Group 12","W":2990,"Z":360},{"C":"Group 13","W":5550,"Z":520},{"C":"Group 14","W":5400,"Z":490},{"C":"Group 15","W":3590,"Z":240},{"C":"Group 16","W":6940,"Z":880},{"C":"Group 18","W":2810,"Z":160},{"C":"Group 17","W":2660,"Z":330},{"C":"Group 19","W":4130,"Z":250},{"C":"Group 20","W":3140,"Z":230},{"C":"Group 21","W":2790,"Z":210},{"C":"Group 22","W":5560,"Z":410},{"C":"Group 23","W":5110,"Z":380},{"C":"Group 0","W":6940,"Z":570},{"C":"Group 1","W":4430,"Z":310},{"C":"Group 2","W":2710,"Z":270},{"C":"Group 3","W":3390,"Z":240},{"C":"Group 4","W":4820,"Z":520},{"C":"Group 5","W":4740,"Z":520},{"C":"Group 6","W":2470,"Z":280},{"C":"Group 7","W":2680,"Z":360},{"C":"Group 8","W":2720,"Z":230},{"C":"Group 9","W":7580,"Z":850},{"C":"Group 10","W":7640,"Z":770},{"C":"Group 11","W":14260,"Z":1270},{"C":"Group 12","W":2930,"Z":390},{"C":"Group 13","W":5430,"Z":560},{"C":"Group 14","W":5280,"Z":510},{"C":"Group 15","W":4290,"Z":280},{"C":"Group 16","W":6880,"Z":930},{"C":"Group 18","W":2780,"Z":180},{"C":"Group 17","W":2640,"Z":350},{"C":"Group 19","W":4810,"Z":290},{"C":"Group 20","W":3120,"Z":240},{"C":"Group 21","W":2800,"Z":220},{"C":"Group 22","W":5370,"Z":430},{"C":"Group 23","W":5510,"Z":420},{"C":"Group 0","W":7040,"Z":600},{"C":"Group 1","W":4310,"Z":320},{"C":"Group 2","W":2800,"Z":290},{"C":"Group 3","W":3550,"Z":260},{"C":"Group 4","W":4750,"Z":540},{"C":"Group 5","W":4660,"Z":530},{"C":"Group 6","W":2430,"Z":290},{"C":"Group 7","W":2660,"Z":370},{"C":"Group 8","W":2780,"Z":240},{"C":"Group 9","W":7500,"Z":880},{"C":"Group 10","W":7490,"Z":800},{"C":"Group 11","W":15810,"Z":1380},{"C":"Group 12","W":2880,"Z":400},{"C":"Group 13","W":5480,"Z":580},{"C":"Group 14","W":5170,"Z":530},{"C":"Group 15","W":4670,"Z":310},{"C":"Group 16","W":6810,"Z":960},{"C":"Group 18","W":2680,"Z":180},{"C":"Group 17","W":2630,"Z":360},{"C":"Group 19","W":5260,"Z":320},{"C":"Group 20","W":3170,"Z":260},{"C":"Group 21","W":2880,"Z":230},{"C":"Group 22","W":5220,"Z":450},{"C":"Group 23","W":5960,"Z":460}]