[{"C":"Group 3","W":10,"Z":64.2},{"C":"Group 3","W":10,"Z":47.1},{"C":"Group 2","W":20,"Z":57.0},{"C":"Group 2","W":13,"Z":46.3},{"C":"Group 3","W":17,"Z":57.4},{"C":"Group 0","W":39,"Z":49.0},{"C":"Group 2","W":9,"Z":50.0},{"C":"Group 0","W":35,"Z":53.5},{"C":"Group 3","W":12,"Z":46.3},{"C":"Group 2","W":10,"Z":59.0},{"C":"Group 2","W":10,"Z":42.9},{"C":"Group 2","W":9,"Z":51.3},{"C":"Group 1","W":12,"Z":50.0},{"C":"Group 3","W":5,"Z":60.9},{"C":"Group 3","W":10,"Z":48.7},{"C":"Group 0","W":36,"Z":48.7}]