[{"C":"Group 8","W":607,"Z":332},{"C":"Group 8","W":667,"Z":370},{"C":"Group 8","W":757,"Z":399},{"C":"Group 8","W":685,"Z":364},{"C":"Group 8","W":752,"Z":430},{"C":"Group 8","W":753,"Z":404},{"C":"Group 8","W":736,"Z":410},{"C":"Group 8","W":869,"Z":478},{"C":"Group 8","W":842,"Z":450},{"C":"Group 8","W":941,"Z":468},{"C":"Group 8","W":912,"Z":504},{"C":"Group 9","W":1269,"Z":575},{"C":"Group 9","W":1315,"Z":687},{"C":"Group 9","W":1356,"Z":715},{"C":"Group 9","W":1187,"Z":671},{"C":"Group 9","W":1310,"Z":727},{"C":"Group 9","W":1420,"Z":754},{"C":"Group 9","W":1465,"Z":762},{"C":"Group 9","W":1622,"Z":792},{"C":"Group 9","W":1576,"Z":801},{"C":"Group 9","W":1592,"Z":818},{"C":"Group 9","W":1733,"Z":856},{"C":"Group 21","W":1188,"Z":689},{"C":"Group 21","W":1460,"Z":898},{"C":"Group 21","W":1528,"Z":921},{"C":"Group 21","W":1435,"Z":836},{"C":"Group 21","W":1799,"Z":1058},{"C":"Group 21","W":1629,"Z":1035},{"C":"Group 21","W":1748,"Z":1066},{"C":"Group 21","W":1913,"Z":1146},{"C":"Group 21","W":2013,"Z":1186},{"C":"Group 21","W":1988,"Z":1212},{"C":"Group 21","W":2244,"Z":1292},{"C":"Group 22","W":1310,"Z":966},{"C":"Group 22","W":1472,"Z":1079},{"C":"Group 22","W":1321,"Z":981},{"C":"Group 22","W":1383,"Z":1012},{"C":"Group 22","W":1536,"Z":1152},{"C":"Group 22","W":1458,"Z":1095},{"C":"Group 22","W":1468,"Z":1057},{"C":"Group 22","W":1616,"Z":1119},{"C":"Group 22","W":1603,"Z":1066},{"C":"Group 22","W":1650,"Z":1122},{"C":"Group 22","W":1677,"Z":1134},{"C":"Group 25","W":1525,"Z":1000},{"C":"Group 25","W":1668,"Z":1178},{"C":"Group 25","W":1616,"Z":1077},{"C":"Group 25","W":1459,"Z":990},{"C":"Group 25","W":1812,"Z":1179},{"C":"Group 25","W":1770,"Z":1037},{"C":"Group 25","W":1741,"Z":1104},{"C":"Group 25","W":1737,"Z":1069},{"C":"Group 25","W":2121,"Z":1240},{"C":"Group 25","W":1775,"Z":1171},{"C":"Group 25","W":1904,"Z":1216},{"C":"Group 14","W":620,"Z":449},{"C":"Group 14","W":614,"Z":440},{"C":"Group 14","W":637,"Z":440},{"C":"Group 14","W":724,"Z":488},{"C":"Group 14","W":679,"Z":472},{"C":"Group 14","W":720,"Z":496},{"C":"Group 14","W":764,"Z":497},{"C":"Group 14","W":885,"Z":571},{"C":"Group 14","W":927,"Z":548},{"C":"Group 14","W":851,"Z":499},{"C":"Group 14","W":1236,"Z":581},{"C":"Group 16","W":2929,"Z":931},{"C":"Group 16","W":4657,"Z":995},{"C":"Group 16","W":4933,"Z":1121},{"C":"Group 16","W":6057,"Z":1103},{"C":"Group 16","W":6896,"Z":1208},{"C":"Group 16","W":8785,"Z":1224},{"C":"Group 16","W":13969,"Z":1271},{"C":"Group 16","W":19061,"Z":1234},{"C":"Group 16","W":30432,"Z":1282},{"C":"Group 16","W":18247,"Z":1259},{"C":"Group 16","W":6021,"Z":1316},{"C":"Group 11","W":1363,"Z":693},{"C":"Group 11","W":1254,"Z":717},{"C":"Group 11","W":1217,"Z":737},{"C":"Group 11","W":1174,"Z":699},{"C":"Group 11","W":1230,"Z":754},{"C":"Group 11","W":1158,"Z":704},{"C":"Group 11","W":1257,"Z":762},{"C":"Group 11","W":1212,"Z":713},{"C":"Group 11","W":1664,"Z":799},{"C":"Group 11","W":1708,"Z":802},{"C":"Group 11","W":1613,"Z":775},{"C":"Group 1","W":389,"Z":308},{"C":"Group 1","W":490,"Z":362},{"C":"Group 1","W":442,"Z":319},{"C":"Group 1","W":395,"Z":313},{"C":"Group 1","W":422,"Z":342},{"C":"Group 1","W":448,"Z":318},{"C":"Group 1","W":386,"Z":285},{"C":"Group 1","W":427,"Z":318},{"C":"Group 1","W":453,"Z":348},{"C":"Group 1","W":445,"Z":331},{"C":"Group 1","W":421,"Z":315},{"C":"Group 10","W":494,"Z":328},{"C":"Group 10","W":484,"Z":344},{"C":"Group 10","W":578,"Z":410},{"C":"Group 10","W":453,"Z":323},{"C":"Group 10","W":459,"Z":330},{"C":"Group 10","W":568,"Z":371},{"C":"Group 10","W":549,"Z":363},{"C":"Group 10","W":671,"Z":426},{"C":"Group 10","W":658,"Z":400},{"C":"Group 10","W":677,"Z":389},{"C":"Group 10","W":717,"Z":371},{"C":"Group 5","W":608,"Z":372},{"C":"Group 5","W":563,"Z":345},{"C":"Group 5","W":602,"Z":324},{"C":"Group 5","W":513,"Z":309},{"C":"Group 5","W":525,"Z":345},{"C":"Group 5","W":549,"Z":375},{"C":"Group 5","W":514,"Z":344},{"C":"Group 5","W":610,"Z":392},{"C":"Group 5","W":545,"Z":312},{"C":"Group 5","W":600,"Z":381},{"C":"Group 5","W":1454,"Z":355},{"C":"Group 15","W":399,"Z":307},{"C":"Group 15","W":396,"Z":317},{"C":"Group 15","W":430,"Z":329},{"C":"Group 15","W":394,"Z":293},{"C":"Group 15","W":380,"Z":285},{"C":"Group 15","W":403,"Z":319},{"C":"Group 15","W":400,"Z":311},{"C":"Group 15","W":376,"Z":273},{"C":"Group 15","W":421,"Z":299},{"C":"Group 15","W":371,"Z":264},{"C":"Group 15","W":411,"Z":319},{"C":"Group 0","W":348,"Z":259},{"C":"Group 0","W":341,"Z":237},{"C":"Group 0","W":399,"Z":268},{"C":"Group 0","W":309,"Z":244},{"C":"Group 0","W":363,"Z":287},{"C":"Group 0","W":306,"Z":234},{"C":"Group 0","W":406,"Z":302},{"C":"Group 0","W":396,"Z":281},{"C":"Group 0","W":403,"Z":318},{"C":"Group 0","W":353,"Z":255},{"C":"Group 0","W":393,"Z":280},{"C":"Group 24","W":276,"Z":213},{"C":"Group 24","W":245,"Z":187},{"C":"Group 24","W":263,"Z":215},{"C":"Group 24","W":283,"Z":233},{"C":"Group 24","W":275,"Z":214},{"C":"Group 24","W":254,"Z":185},{"C":"Group 24","W":257,"Z":196},{"C":"Group 24","W":258,"Z":195},{"C":"Group 24","W":284,"Z":207},{"C":"Group 24","W":306,"Z":239},{"C":"Group 24","W":288,"Z":222},{"C":"Group 19","W":454,"Z":346},{"C":"Group 19","W":411,"Z":322},{"C":"Group 19","W":485,"Z":369},{"C":"Group 19","W":452,"Z":375},{"C":"Group 19","W":441,"Z":367},{"C":"Group 19","W":419,"Z":344},{"C":"Group 19","W":420,"Z":336},{"C":"Group 19","W":509,"Z":404},{"C":"Group 19","W":474,"Z":360},{"C":"Group 19","W":489,"Z":353},{"C":"Group 19","W":520,"Z":390},{"C":"Group 23","W":557,"Z":368},{"C":"Group 23","W":694,"Z":450},{"C":"Group 23","W":637,"Z":401},{"C":"Group 23","W":706,"Z":464},{"C":"Group 23","W":733,"Z":486},{"C":"Group 23","W":673,"Z":443},{"C":"Group 23","W":767,"Z":494},{"C":"Group 23","W":748,"Z":504},{"C":"Group 23","W":714,"Z":452},{"C":"Group 23","W":753,"Z":482},{"C":"Group 23","W":804,"Z":451},{"C":"Group 18","W":280,"Z":187},{"C":"Group 18","W":284,"Z":194},{"C":"Group 18","W":272,"Z":187},{"C":"Group 18","W":277,"Z":194},{"C":"Group 18","W":322,"Z":230},{"C":"Group 18","W":278,"Z":193},{"C":"Group 18","W":267,"Z":202},{"C":"Group 18","W":309,"Z":224},{"C":"Group 18","W":362,"Z":246},{"C":"Group 18","W":339,"Z":209},{"C":"Group 18","W":364,"Z":196},{"C":"Group 6","W":410,"Z":312},{"C":"Group 6","W":420,"Z":289},{"C":"Group 6","W":389,"Z":275},{"C":"Group 6","W":437,"Z":331},{"C":"Group 6","W":428,"Z":319},{"C":"Group 6","W":440,"Z":329},{"C":"Group 6","W":427,"Z":303},{"C":"Group 6","W":503,"Z":339},{"C":"Group 6","W":461,"Z":315},{"C":"Group 6","W":481,"Z":319},{"C":"Group 6","W":440,"Z":308},{"C":"Group 2","W":1595,"Z":1107},{"C":"Group 2","W":1618,"Z":1103},{"C":"Group 2","W":1521,"Z":1072},{"C":"Group 2","W":1611,"Z":1197},{"C":"Group 2","W":1651,"Z":1221},{"C":"Group 2","W":1687,"Z":1207},{"C":"Group 2","W":1678,"Z":1161},{"C":"Group 2","W":1669,"Z":1156},{"C":"Group 2","W":1676,"Z":1132},{"C":"Group 2","W":1695,"Z":1161},{"C":"Group 2","W":1731,"Z":1185},{"C":"Group 3","W":427,"Z":357},{"C":"Group 3","W":438,"Z":347},{"C":"Group 3","W":446,"Z":360},{"C":"Group 3","W":455,"Z":382},{"C":"Group 3","W":490,"Z":394},{"C":"Group 3","W":465,"Z":383},{"C":"Group 3","W":457,"Z":372},{"C":"Group 3","W":451,"Z":335},{"C":"Group 3","W":545,"Z":385},{"C":"Group 3","W":480,"Z":340},{"C":"Group 3","W":484,"Z":321},{"C":"Group 20","W":116,"Z":101},{"C":"Group 20","W":88,"Z":74},{"C":"Group 20","W":135,"Z":116},{"C":"Group 20","W":103,"Z":95},{"C":"Group 20","W":160,"Z":139},{"C":"Group 20","W":89,"Z":83},{"C":"Group 20","W":113,"Z":100},{"C":"Group 20","W":179,"Z":146},{"C":"Group 20","W":157,"Z":115},{"C":"Group 20","W":143,"Z":98},{"C":"Group 20","W":180,"Z":128},{"C":"Group 7","W":101,"Z":87},{"C":"Group 7","W":89,"Z":77},{"C":"Group 7","W":126,"Z":100},{"C":"Group 7","W":112,"Z":102},{"C":"Group 7","W":105,"Z":85},{"C":"Group 7","W":107,"Z":89},{"C":"Group 7","W":85,"Z":66},{"C":"Group 7","W":95,"Z":88},{"C":"Group 7","W":98,"Z":83},{"C":"Group 7","W":99,"Z":81},{"C":"Group 7","W":108,"Z":87},{"C":"Group 26","W":154,"Z":121},{"C":"Group 26","W":186,"Z":133},{"C":"Group 26","W":160,"Z":130},{"C":"Group 26","W":170,"Z":138},{"C":"Group 26","W":142,"Z":125},{"C":"Group 26","W":153,"Z":123},{"C":"Group 26","W":158,"Z":131},{"C":"Group 26","W":173,"Z":149},{"C":"Group 26","W":173,"Z":127},{"C":"Group 26","W":163,"Z":120},{"C":"Group 26","W":146,"Z":120},{"C":"Group 4","W":149,"Z":132},{"C":"Group 4","W":152,"Z":124},{"C":"Group 4","W":131,"Z":113},{"C":"Group 4","W":166,"Z":137},{"C":"Group 4","W":184,"Z":154},{"C":"Group 4","W":156,"Z":142},{"C":"Group 4","W":139,"Z":115},{"C":"Group 4","W":184,"Z":153},{"C":"Group 4","W":168,"Z":136},{"C":"Group 4","W":188,"Z":144},{"C":"Group 4","W":165,"Z":144},{"C":"Group 17","W":81,"Z":74},{"C":"Group 17","W":70,"Z":65},{"C":"Group 17","W":72,"Z":60},{"C":"Group 17","W":74,"Z":70},{"C":"Group 17","W":78,"Z":65},{"C":"Group 17","W":79,"Z":71},{"C":"Group 17","W":91,"Z":68},{"C":"Group 17","W":94,"Z":69},{"C":"Group 17","W":79,"Z":68},{"C":"Group 17","W":102,"Z":83},{"C":"Group 17","W":74,"Z":61},{"C":"Group 12","W":871,"Z":685},{"C":"Group 12","W":858,"Z":647},{"C":"Group 12","W":942,"Z":699},{"C":"Group 12","W":801,"Z":628},{"C":"Group 12","W":870,"Z":685},{"C":"Group 12","W":892,"Z":668},{"C":"Group 12","W":910,"Z":628},{"C":"Group 12","W":1007,"Z":708},{"C":"Group 12","W":1017,"Z":698},{"C":"Group 12","W":1106,"Z":730},{"C":"Group 12","W":1067,"Z":716},{"C":"Group 13","W":507,"Z":335},{"C":"Group 13","W":445,"Z":312},{"C":"Group 13","W":502,"Z":364},{"C":"Group 13","W":455,"Z":344},{"C":"Group 13","W":460,"Z":327},{"C":"Group 13","W":503,"Z":340},{"C":"Group 13","W":510,"Z":373},{"C":"Group 13","W":564,"Z":364},{"C":"Group 13","W":580,"Z":364},{"C":"Group 13","W":573,"Z":382},{"C":"Group 13","W":571,"Z":382}]