[{"C":"Group 1","W":25.29,"Z":33.819},{"C":"Group 0","W":0.0,"Z":128.62},{"C":"Group 3","W":653.582,"Z":597.134},{"C":"Group 6","W":107.196,"Z":153.585},{"C":"Group 7","W":32149.6,"Z":76615.5},{"C":"Group 4","W":154145.0,"Z":181174.0},{"C":"Group 5","W":285957.0,"Z":538752.0},{"C":"Group 1","W":14271.067,"Z":12803.186},{"C":"Group 0","W":0.0,"Z":253.157},{"C":"Group 5","W":521.234,"Z":982.021},{"C":"Group 3","W":332.063,"Z":303.383},{"C":"Group 7","W":29.717,"Z":70.819},{"C":"Group 5","W":176.547,"Z":332.621},{"C":"Group 0","W":0.0,"Z":12132.7},{"C":"Group 7","W":87.736,"Z":209.084},{"C":"Group 6","W":45379.1,"Z":65017.1},{"C":"Group 4","W":61.055,"Z":71.762},{"C":"Group 2","W":0.729,"Z":1.351},{"C":"Group 2","W":2.153,"Z":3.987},{"C":"Group 3","W":42809.1,"Z":39111.6},{"C":"Group 1","W":2889820.0,"Z":2595600.0},{"C":"Group 7","W":8037.4,"Z":19153.9},{"C":"Group 1","W":6445.005,"Z":5782.077},{"C":"Group 4","W":90.129,"Z":105.934},{"C":"Group 6","W":36.308,"Z":52.021},{"C":"Group 2","W":846.226,"Z":1566.94}]