[{"C":"Group 0","W":5776440,"Z":2422001},{"C":"Group 3","W":263967,"Z":280493},{"C":"Group 6","W":2746432,"Z":3526833},{"C":"Group 8","W":7496,"Z":4626},{"C":"Group 10","W":4448,"Z":6233},{"C":"Group 9","W":2102206,"Z":936724},{"C":"Group 4","W":1145,"Z":910},{"C":"Group 4","W":7105,"Z":6293},{"C":"Group 4","W":3617132,"Z":3318487},{"C":"Group 2","W":171469,"Z":256774},{"C":"Group 4","W":6227,"Z":7000},{"C":"Group 8","W":1303976,"Z":1480761},{"C":"Group 10","W":362203,"Z":507750},{"C":"Group 2","W":650253,"Z":677789},{"C":"Group 4","W":25949,"Z":24822},{"C":"Group 5","W":61203,"Z":49328},{"C":"Group 0","W":20104329,"Z":14541479},{"C":"Group 4","W":17596,"Z":21006},{"C":"Group 2","W":449811,"Z":765691},{"C":"Group 10","W":540406,"Z":648813},{"C":"Group 4","W":40227,"Z":24994},{"C":"Group 9","W":1494955,"Z":652962},{"C":"Group 7","W":3762,"Z":3802},{"C":"Group 0","W":68067,"Z":64068},{"C":"Group 4","W":993436,"Z":807082},{"C":"Group 3","W":195822,"Z":323810},{"C":"Group 9","W":204131,"Z":190912},{"C":"Group 4","W":18010731,"Z":17567444},{"C":"Group 0","W":33926,"Z":37399},{"C":"Group 3","W":344062,"Z":527156},{"C":"Group 9","W":2806508,"Z":1163247},{"C":"Group 0","W":3938519,"Z":4671155},{"C":"Group 9","W":1568594,"Z":665175},{"C":"Group 0","W":1621832,"Z":1335501},{"C":"Group 9","W":2858343,"Z":1516914},{"C":"Group 7","W":1707051,"Z":2234883},{"C":"Group 9","W":48977,"Z":30342},{"C":"Group 4","W":3129,"Z":2960},{"C":"Group 9","W":655308,"Z":353839},{"C":"Group 9","W":1805046,"Z":695940},{"C":"Group 4","W":1223944,"Z":1301893},{"C":"Group 0","W":84554345,"Z":99146104},{"C":"Group 4","W":4380574,"Z":3467187},{"C":"Group 9","W":116677,"Z":56031},{"C":"Group 9","W":695566,"Z":284823},{"C":"Group 9","W":12165701,"Z":4925666},{"C":"Group 8","W":1015,"Z":597},{"C":"Group 4","W":370562,"Z":350749},{"C":"Group 9","W":2984624,"Z":1655972},{"C":"Group 3","W":214265,"Z":321088},{"C":"Group 4","W":664247,"Z":651989},{"C":"Group 5","W":49007,"Z":60413},{"C":"Group 3","W":461047,"Z":760601},{"C":"Group 10","W":309469,"Z":310943},{"C":"Group 9","W":83703,"Z":40971},{"C":"Group 4","W":5573,"Z":5907},{"C":"Group 4","W":1032127,"Z":764337},{"C":"Group 4","W":1469914,"Z":1206983},{"C":"Group 6","W":8749490,"Z":7012515},{"C":"Group 4","W":879892,"Z":595526},{"C":"Group 9","W":98908,"Z":46097},{"C":"Group 9","W":886221,"Z":444495},{"C":"Group 1","W":65905,"Z":92310},{"C":"Group 9","W":15341622,"Z":6403123},{"C":"Group 10","W":3420,"Z":2621},{"C":"Group 8","W":99750,"Z":84061},{"C":"Group 10","W":274070,"Z":328237},{"C":"Group 10","W":4061477,"Z":4142530},{"C":"Group 8","W":22720,"Z":23815},{"C":"Group 9","W":237600,"Z":110229},{"C":"Group 9","W":290573,"Z":129176},{"C":"Group 5","W":263009,"Z":114496},{"C":"Group 2","W":234787,"Z":317098},{"C":"Group 10","W":3448106,"Z":4848333},{"C":"Group 9","W":3182079,"Z":1872517},{"C":"Group 10","W":1505,"Z":1892},{"C":"Group 10","W":514279,"Z":768069},{"C":"Group 7","W":4268,"Z":3613},{"C":"Group 4","W":9734,"Z":8594},{"C":"Group 8","W":15950,"Z":11967},{"C":"Group 4","W":1775409,"Z":1000431},{"C":"Group 10","W":2923,"Z":3854},{"C":"Group 9","W":1617207,"Z":729448},{"C":"Group 9","W":232607,"Z":122603},{"C":"Group 4","W":67505,"Z":75871},{"C":"Group 4","W":1399192,"Z":750829},{"C":"Group 4","W":1004711,"Z":642635},{"C":"Group 0","W":257608,"Z":494923},{"C":"Group 3","W":482506,"Z":722275},{"C":"Group 10","W":20484,"Z":22696},{"C":"Group 0","W":123363700,"Z":96059863},{"C":"Group 0","W":22434977,"Z":20600588},{"C":"Group 0","W":4938296,"Z":7265633},{"C":"Group 5","W":4032729,"Z":2504288},{"C":"Group 10","W":296592,"Z":336630},{"C":"Group 10","W":4193,"Z":4911},{"C":"Group 5","W":705198,"Z":535877},{"C":"Group 10","W":2551912,"Z":3366464},{"C":"Group 4","W":281353,"Z":255762},{"C":"Group 0","W":5363680,"Z":7790091},{"C":"Group 10","W":4331,"Z":4611},{"C":"Group 5","W":629098,"Z":571227},{"C":"Group 2","W":1162869,"Z":1329871},{"C":"Group 9","W":6525155,"Z":3453614},{"C":"Group 8","W":15133,"Z":8178},{"C":"Group 0","W":1776990,"Z":1704495},{"C":"Group 0","W":2243650,"Z":4081026},{"C":"Group 5","W":261958,"Z":400645},{"C":"Group 2","W":562346,"Z":464504},{"C":"Group 0","W":1012162,"Z":547142},{"C":"Group 1","W":103103,"Z":159578},{"C":"Group 5","W":349800,"Z":386167},{"C":"Group 9","W":242683,"Z":191615},{"C":"Group 9","W":576093,"Z":256832},{"C":"Group 6","W":756468,"Z":598203},{"C":"Group 10","W":1766,"Z":2115},{"C":"Group 1","W":154470,"Z":256642},{"C":"Group 10","W":29190,"Z":31500},{"C":"Group 0","W":27023,"Z":45791},{"C":"Group 3","W":121382,"Z":164247},{"C":"Group 9","W":3370479,"Z":1495660},{"C":"Group 9","W":2448140,"Z":1121808},{"C":"Group 0","W":2725293,"Z":1963422},{"C":"Group 0","W":26555,"Z":45191},{"C":"Group 9","W":2424065,"Z":934501},{"C":"Group 10","W":20313,"Z":29472},{"C":"Group 8","W":9322,"Z":5773},{"C":"Group 9","W":588030,"Z":251630},{"C":"Group 9","W":93640,"Z":113801},{"C":"Group 9","W":37983,"Z":14504},{"C":"Group 4","W":10772705,"Z":9073064},{"C":"Group 8","W":12421,"Z":8947},{"C":"Group 2","W":223656,"Z":377187},{"C":"Group 10","W":1500,"Z":1662},{"C":"Group 0","W":287865,"Z":279155},{"C":"Group 3","W":36805,"Z":59631},{"C":"Group 4","W":270,"Z":522},{"C":"Group 6","W":3496612,"Z":3101010},{"C":"Group 9","W":3465510,"Z":1522274},{"C":"Group 9","W":240942,"Z":195869},{"C":"Group 8","W":1629,"Z":1165},{"C":"Group 0","W":4032157,"Z":2528922},{"C":"Group 10","W":914123,"Z":1010219},{"C":"Group 4","W":16310,"Z":15529},{"C":"Group 8","W":19784,"Z":17531},{"C":"Group 8","W":290939,"Z":266907},{"C":"Group 4","W":661881,"Z":527969},{"C":"Group 9","W":2567566,"Z":941442},{"C":"Group 9","W":23206064,"Z":11882992},{"C":"Group 8","W":6189,"Z":12965},{"C":"Group 10","W":267804,"Z":275987},{"C":"Group 5","W":545515,"Z":239813},{"C":"Group 0","W":22559212,"Z":13950152},{"C":"Group 8","W":1829,"Z":1405},{"C":"Group 4","W":332769,"Z":265200},{"C":"Group 8","W":786027,"Z":490377},{"C":"Group 4","W":912147,"Z":508615},{"C":"Group 4","W":2818031,"Z":2426508},{"C":"Group 0","W":12114349,"Z":8301098},{"C":"Group 3","W":1864722,"Z":3277245},{"C":"Group 10","W":571451,"Z":761877},{"C":"Group 4","W":245894,"Z":281985},{"C":"Group 5","W":62293,"Z":91860},{"C":"Group 3","W":1159263,"Z":1766032},{"C":"Group 2","W":7513959,"Z":11100042},{"C":"Group 9","W":1704439,"Z":901140},{"C":"Group 4","W":479,"Z":636},{"C":"Group 9","W":448,"Z":541},{"C":"Group 4","W":3450,"Z":3218},{"C":"Group 4","W":12014,"Z":12523},{"C":"Group 4","W":2740,"Z":2727},{"C":"Group 7","W":471,"Z":356},{"C":"Group 4","W":9263,"Z":11655},{"C":"Group 8","W":28859,"Z":15695},{"C":"Group 10","W":1588,"Z":1832},{"C":"Group 9","W":36840,"Z":15375},{"C":"Group 5","W":3984299,"Z":2958787},{"C":"Group 9","W":2111235,"Z":1041399},{"C":"Group 3","W":607724,"Z":745898},{"C":"Group 9","W":6395,"Z":7500},{"C":"Group 9","W":1106341,"Z":457669},{"C":"Group 0","W":209449,"Z":340955},{"C":"Group 3","W":286620,"Z":458509},{"C":"Group 3","W":89754,"Z":150044},{"C":"Group 8","W":80856,"Z":48879},{"C":"Group 9","W":1730104,"Z":676731},{"C":"Group 9","W":4723768,"Z":4502651},{"C":"Group 10","W":2023721,"Z":2880313},{"C":"Group 0","W":1757259,"Z":1880570},{"C":"Group 9","W":5977040,"Z":3206722},{"C":"Group 4","W":40553,"Z":41101},{"C":"Group 9","W":143450,"Z":101556},{"C":"Group 10","W":466410,"Z":533199},{"C":"Group 10","W":368735,"Z":479235},{"C":"Group 5","W":2531377,"Z":1826868},{"C":"Group 0","W":1044117,"Z":1991763},{"C":"Group 2","W":889681,"Z":622071},{"C":"Group 9","W":6376827,"Z":3254691},{"C":"Group 0","W":4381755,"Z":5602217},{"C":"Group 0","W":135452,"Z":84691},{"C":"Group 9","W":936103,"Z":489421},{"C":"Group 8","W":13648,"Z":10736},{"C":"Group 4","W":63987,"Z":97633},{"C":"Group 6","W":767274,"Z":1006710},{"C":"Group 5","W":5619960,"Z":6562361},{"C":"Group 2","W":605799,"Z":423742},{"C":"Group 4","W":2304,"Z":1498},{"C":"Group 8","W":1262,"Z":962},{"C":"Group 9","W":6318612,"Z":2251178},{"C":"Group 2","W":2129415,"Z":3559569},{"C":"Group 5","W":370767,"Z":681349},{"C":"Group 10","W":3246306,"Z":3982630},{"C":"Group 7","W":21009914,"Z":21161376},{"C":"Group 4","W":249861,"Z":262801},{"C":"Group 2","W":2418997,"Z":2428294},{"C":"Group 8","W":22323,"Z":20089},{"C":"Group 4","W":2695974,"Z":2182511},{"C":"Group 0","W":6898580,"Z":7928649},{"C":"Group 4","W":1686,"Z":2259},{"C":"Group 4","W":7352,"Z":5703},{"C":"Group 8","W":1174,"Z":1200},{"C":"Group 5","W":304739,"Z":197220},{"C":"Group 6","W":68119,"Z":28719},{"C":"Group 5","W":4230900,"Z":1872119},{"C":"Group 9","W":1986918,"Z":993626},{"C":"Group 9","W":1752774,"Z":891189}]