[{"C":"Group 2","W":22.3,"Z":16.3},{"C":"Group 2","W":22.9,"Z":16.1},{"C":"Group 2","W":21.9,"Z":15.5},{"C":"Group 2","W":21.6,"Z":14.9},{"C":"Group 1","W":20.5,"Z":14.6},{"C":"Group 1","W":22.1,"Z":15.2},{"C":"Group 1","W":22.3,"Z":15.2},{"C":"Group 1","W":22.0,"Z":15.3},{"C":"Group 1","W":20.8,"Z":15.1},{"C":"Group 1","W":19.2,"Z":15.3},{"C":"Group 2","W":19.8,"Z":16.3},{"C":"Group 2","W":18.5,"Z":15.4},{"C":"Group 2","W":18.1,"Z":14.9},{"C":"Group 0","W":17.5,"Z":13.7},{"C":"Group 0","W":17.3,"Z":12.7},{"C":"Group 0","W":16.9,"Z":12.2},{"C":"Group 0","W":16.8,"Z":12.2},{"C":"Group 0","W":16.0,"Z":12.1},{"C":"Group 0","W":16.3,"Z":11.6},{"C":"Group 0","W":16.8,"Z":13.1}]