[{"C":"Group 5","W":243620,"Z":259378},{"C":"Group 5","W":364004,"Z":351041},{"C":"Group 5","W":1961351,"Z":2258068},{"C":"Group 1","W":57250,"Z":61382},{"C":"Group 1","W":118802,"Z":138329},{"C":"Group 1","W":493389,"Z":575969},{"C":"Group 2","W":1996,"Z":1439},{"C":"Group 2","W":3493,"Z":2878},{"C":"Group 2","W":17126,"Z":12828},{"C":"Group 3","W":116998,"Z":87971},{"C":"Group 3","W":203240,"Z":208359},{"C":"Group 3","W":2237492,"Z":2246639},{"C":"Group 4","W":251963,"Z":266080},{"C":"Group 4","W":801767,"Z":834679},{"C":"Group 4","W":3215835,"Z":3457753},{"C":"Group 0","W":15,"Z":75},{"C":"Group 0","W":32639,"Z":41333},{"C":"Group 0","W":89577,"Z":110812}]