[{"C":"Group 1","W":150,"Z":12},{"C":"Group 0","W":111,"Z":8},{"C":"Group 3","W":107,"Z":10},{"C":"Group 1","W":156,"Z":14},{"C":"Group 2","W":181,"Z":27},{"C":"Group 5","W":140,"Z":10},{"C":"Group 3","W":88,"Z":14},{"C":"Group 3","W":72,"Z":7},{"C":"Group 3","W":87,"Z":13},{"C":"Group 3","W":84,"Z":16},{"C":"Group 3","W":88,"Z":14},{"C":"Group 4","W":148,"Z":14},{"C":"Group 5","W":186,"Z":22},{"C":"Group 1","W":160,"Z":16},{"C":"Group 2","W":152,"Z":8},{"C":"Group 4","W":145,"Z":20},{"C":"Group 3","W":95,"Z":12},{"C":"Group 1","W":157,"Z":16},{"C":"Group 5","W":182,"Z":15},{"C":"Group 2","W":168,"Z":15},{"C":"Group 4","W":159,"Z":18},{"C":"Group 4","W":179,"Z":8},{"C":"Group 2","W":200,"Z":20},{"C":"Group 4","W":182,"Z":18},{"C":"Group 5","W":211,"Z":18},{"C":"Group 0","W":109,"Z":2},{"C":"Group 3","W":93,"Z":8},{"C":"Group 3","W":89,"Z":8},{"C":"Group 0","W":115,"Z":12},{"C":"Group 3","W":136,"Z":6},{"C":"Group 2","W":182,"Z":12}]